{"version": 0.6, "generator": "Overpass API 0.7.62.1 084b4234", "osm3s": {"timestamp_osm_base": "2024-09-30T22:49:29Z", "copyright": "The data included in this document is from www.openstreetmap.org. The data is made available under ODbL."}, "elements": [{"type": "node", "id": 4933918660, "lat": 6.8771706, "lon": 38.5842966}, {"type": "node", "id": 4933918661, "lat": 6.8771253, "lon": 38.584935}, {"type": "node", "id": 4933918662, "lat": 6.8768114, "lon": 38.5849124}, {"type": "node", "id": 4933918663, "lat": 6.8768567, "lon": 38.5842741}, {"type": "node", "id": 4985926491, "lat": 6.986164, "lon": 38.5320162}, {"type": "node", "id": 4985926492, "lat": 6.9857034, "lon": 38.531866}, {"type": "node", "id": 4985926493, "lat": 6.9857998, "lon": 38.531566}, {"type": "node", "id": 4985926494, "lat": 6.9862604, "lon": 38.5317162}, {"type": "node", "id": 9918144099, "lat": 6.6894349, "lon": 38.7127848}, {"type": "node", "id": 9918144100, "lat": 6.6885052, "lon": 38.71264}, {"type": "node", "id": 9918144101, "lat": 6.688605, "lon": 38.7119901}, {"type": "node", "id": 9918144102, "lat": 6.6895348, "lon": 38.712135}, {"type": "way", "id": 503038323, "nodes": [4933918663, 4933918660, 4933918661, 4933918662, 4933918663], "tags": {"leisure": "pitch", "sport": "soccer"}}, {"type": "way", "id": 509342600, "nodes": [4985926494, 4985926491, 4985926492, 4985926493, 4985926494], "tags": {"leisure": "pitch", "sport": "soccer"}}, {"type": "way", "id": 1082220125, "nodes": [9918144102, 9918144099, 9918144100, 9918144101, 9918144102], "tags": {"leisure": "pitch", "sport": "soccer"}}]}