{"version": 0.6, "generator": "Overpass API 0.7.62.1 084b4234", "osm3s": {"timestamp_osm_base": "2024-11-17T21:42:15Z", "copyright": "The data included in this document is from www.openstreetmap.org. The data is made available under ODbL."}, "elements": [{"type": "node", "id": 313941532, "lat": 9.9561523, "lon": 49.0537801, "tags": {"name": "Xidda", "place": "town"}}, {"type": "node", "id": 1404221893, "lat": 9.9738277, "lon": 48.97958, "tags": {"fixme": "Please, check location!", "name": "Kalad Hacda", "pcode": "NC-3909-A22-001", "place": "hamlet", "source": "GTZ - 2002"}}, {"type": "node", "id": 1404222190, "lat": 10.136301, "lon": 49.011269, "tags": {"alt_name": "Qayadsame", "fixme": "Please, check location!", "name": "Qayaad Samo", "pcode": "NC-3905-W23-001", "place": "hamlet", "source": "UNDP - 2006, GTZ - 2002, UNDP - 1997"}}, {"type": "node", "id": 1404222938, "lat": 10.0854812, "lon": 49.0296791, "tags": {"alt_name": "Alhamdulilah", "name": "Alxamdullileh", "pcode": "NC-3905-X23-001", "place": "village", "source": "UNDP - 2006, GTZ - 2002, UNDP - 1997"}}, {"type": "node", "id": 1404225742, "lat": 10.0484161, "lon": 48.8924762, "tags": {"name": "Bali Busle", "pcode": "NC-3905-Y20-003", "place": "hamlet", "source": "UNDP - 2006"}}, {"type": "node", "id": 1404231604, "lat": 10.047619, "lon": 48.899384, "tags": {"name": "Cawsane", "pcode": "NC-3905-Y20-001", "place": "hamlet", "source": "GTZ - 2002"}}, {"type": "node", "id": 1404231759, "lat": 10.0560366, "lon": 48.9071949, "tags": {"alt_name": "Kala Dhacda", "name": "Kaladhac", "pcode": "NC-3905-Y20-004", "place": "village", "source": "UNDP - 2006, FSAU"}}, {"type": "node", "id": 1404233026, "lat": 10.04351, "lon": 48.89102, "tags": {"name": "Habar Shiro", "pcode": "NC-3905-Y20-002", "place": "hamlet", "source": "UNDP - 2006"}}, {"type": "node", "id": 1404233451, "lat": 10.0119611, "lon": 49.0431561, "tags": {"name": "Waaciye", "name:ar": "\u0648\u0627\u0639\u064a", "pcode": "NC-3905-Z23-001", "place": "town", "source": "UNDP - 2006, GTZ - 2002, UNDP - 1997"}}]}