{"version": 0.6, "generator": "Overpass API 0.7.62.1 084b4234", "osm3s": {"timestamp_osm_base": "2024-09-30T18:49:41Z", "copyright": "The data included in this document is from www.openstreetmap.org. The data is made available under ODbL."}, "elements": [{"type": "node", "id": 5501781661, "lat": -0.0968829, "lon": 39.0464795, "tags": {"name": "Mbalambala", "place": "hamlet"}}, {"type": "node", "id": 5505461198, "lat": -0.2733424, "lon": 38.9154659, "tags": {"place": "hamlet"}}, {"type": "node", "id": 5505491803, "lat": -0.0558138, "lon": 38.9685283, "tags": {"name": "Mudey", "place": "hamlet"}}, {"type": "node", "id": 5505559267, "lat": -0.0427211, "lon": 39.0614065, "tags": {"name": "Halane", "place": "village"}}, {"type": "node", "id": 7101233012, "lat": -0.0582468, "lon": 38.968302, "tags": {"place": "village"}}, {"type": "node", "id": 7340234439, "lat": -0.0847041, "lon": 39.0318811}, {"type": "node", "id": 7340234440, "lat": -0.0849831, "lon": 39.0327394}, {"type": "node", "id": 7340234441, "lat": -0.0852191, "lon": 39.0336621}, {"type": "node", "id": 7340234442, "lat": -0.0854551, "lon": 39.0342951}, {"type": "node", "id": 7340234443, "lat": -0.0858306, "lon": 39.0351105}, {"type": "node", "id": 7340234444, "lat": -0.0858843, "lon": 39.0360331}, {"type": "node", "id": 7340234445, "lat": -0.0850367, "lon": 39.0357005}, {"type": "node", "id": 7340234446, "lat": -0.0847256, "lon": 39.0349924}, {"type": "node", "id": 7340234447, "lat": -0.084511, "lon": 39.0343273}, {"type": "node", "id": 7340234448, "lat": -0.0845003, "lon": 39.0333509}, {"type": "node", "id": 7340234449, "lat": -0.0842106, "lon": 39.0324712}, {"type": "node", "id": 7340234450, "lat": -0.084393, "lon": 39.0315807}, {"type": "node", "id": 7340234451, "lat": -0.0888884, "lon": 39.0188241}, {"type": "node", "id": 7340234452, "lat": -0.088824, "lon": 39.0195322}, {"type": "node", "id": 7340234453, "lat": -0.0883626, "lon": 39.0206587}, {"type": "node", "id": 7340234454, "lat": -0.0879335, "lon": 39.0215063}, {"type": "node", "id": 7340234455, "lat": -0.0871932, "lon": 39.0226328}, {"type": "node", "id": 7340234456, "lat": -0.0863242, "lon": 39.0235126}, {"type": "node", "id": 7340234457, "lat": -0.0858414, "lon": 39.0246177}, {"type": "node", "id": 7340234458, "lat": -0.0853264, "lon": 39.0257335}, {"type": "node", "id": 7340234459, "lat": -0.0852084, "lon": 39.0271497}, {"type": "node", "id": 7340234460, "lat": -0.0848651, "lon": 39.026463}, {"type": "node", "id": 7340234461, "lat": -0.0845432, "lon": 39.0257227}, {"type": "node", "id": 7340234462, "lat": -0.0838887, "lon": 39.0248322}, {"type": "node", "id": 7340234463, "lat": -0.083245, "lon": 39.0239525}, {"type": "node", "id": 7340234464, "lat": -0.0828051, "lon": 39.022268}, {"type": "node", "id": 7340234465, "lat": -0.0826013, "lon": 39.0213239}, {"type": "node", "id": 7340234466, "lat": -0.0828051, "lon": 39.0202403}, {"type": "node", "id": 7340234467, "lat": -0.0834596, "lon": 39.0197039}, {"type": "node", "id": 7340234468, "lat": -0.0843501, "lon": 39.0189743}, {"type": "node", "id": 7340234469, "lat": -0.0854337, "lon": 39.0185773}, {"type": "node", "id": 7340234470, "lat": -0.0861847, "lon": 39.0185559}, {"type": "node", "id": 7340234471, "lat": -0.0869143, "lon": 39.0185559}, {"type": "node", "id": 7340234472, "lat": -0.0873541, "lon": 39.0184486}, {"type": "node", "id": 7340234473, "lat": -0.0888884, "lon": 39.0180623}, {"type": "node", "id": 11375930859, "lat": -0.0434272, "lon": 39.011355, "tags": {"name": "Jarajara", "place": "village"}}, {"type": "node", "id": 11375930860, "lat": -0.0358016, "lon": 39.0277359, "tags": {"name": "Abaaq alol", "place": "hamlet"}}, {"type": "node", "id": 11375942571, "lat": -0.0312421, "lon": 38.9858574, "tags": {"name": "Kone", "place": "hamlet"}}, {"type": "node", "id": 11376024047, "lat": -0.0616837, "lon": 39.1112401, "tags": {"name": "Kuno", "place": "hamlet"}}, {"type": "node", "id": 11376024048, "lat": -0.0615234, "lon": 39.141329, "tags": {"name": "Kasha", "place": "hamlet"}}, {"type": "node", "id": 11802184650, "lat": -0.0583741, "lon": 38.9319506, "tags": {"name": "Scot", "place": "hamlet"}}, {"type": "way", "id": 785328120, "nodes": [7340234450, 7340234449, 7340234448, 7340234447, 7340234446, 7340234445, 7340234444, 7340234443, 7340234442, 7340234441, 7340234440, 7340234439, 7340234450], "tags": {"place": "islet"}}, {"type": "way", "id": 785328121, "nodes": [7340234473, 7340234472, 7340234471, 7340234470, 7340234469, 7340234468, 7340234467, 7340234466, 7340234465, 7340234464, 7340234463, 7340234462, 7340234461, 7340234460, 7340234459, 7340234458, 7340234457, 7340234456, 7340234455, 7340234454, 7340234453, 7340234452, 7340234451, 7340234473], "tags": {"place": "islet"}}]}