{"version": 0.6, "generator": "Overpass API 0.7.62.1 084b4234", "osm3s": {"timestamp_osm_base": "2024-09-30T20:39:55Z", "copyright": "The data included in this document is from www.openstreetmap.org. The data is made available under ODbL."}, "elements": [{"type": "node", "id": 35776957, "lat": 0.6758822, "lon": 43.5183907}, {"type": "node", "id": 36155607, "lat": 4.1237042, "lon": 43.8915563, "tags": {"name": "Xudur \u062d\u0648\u062f\u0648\u0631", "name:ar": "\u062d\u0648\u062f\u0648\u0631", "name:de": "Huddur", "name:en": "Hudur", "name:es": "Xudur", "name:fr": "Xuddur", "name:ko": "\ud6c4\ub450\ub974", "name:ru": "\u0425\u0443\u0434\u0434\u0443\u0440", "place": "city", "wikidata": "Q1017160", "wikipedia": "en:Hudur"}}, {"type": "node", "id": 43527946, "lat": 1.112777, "lon": 44.031005, "tags": {"alt_name": "Baraawe", "name": "Baraawe \u0645\u062f\u064a\u0646\u0629 \ufe91\ufeae\ufe8d\ufeed\u0629", "name:ar": "\u0645\u062f\u064a\u0646\u0629 \ufe91\ufeae\ufe8d\ufeed\u0629", "name:en": "Barawa", "name:fr": "Brava", "name:lt": "Barava", "name:zh": "\u5e03\u62c9\u74e6", "place": "town", "wikidata": "Q613246", "wikipedia": "en:Barawa"}}, {"type": "node", "id": 43527998, "lat": 4.000003, "lon": 43.999993, "tags": {"name": "Bakool \u0628\u0627\u0643\u0648\u0644", "name:ar": "\u0628\u0627\u0643\u0648\u0644", "name:en": "Bakool", "name:fr": "Bakool", "name:hu": "Bakool", "name:ru": "\u0411\u0430\u043a\u043e\u043b\u044c", "place": "state", "ref": "BK", "state_code": "BK"}}, {"type": "node", "id": 43528040, "lat": 3.0, "lon": 42.0, "tags": {"name": "Gedo \u062c\u062f\u0648", "name:ar": "\u062c\u062f\u0648", "name:en": "Gedo", "name:fr": "Gedo", "name:it": "Ghedo", "name:ru": "\u0413\u0435\u0434\u043e", "place": "state", "ref": "GD", "state_code": "GD"}}, {"type": "node", "id": 43528307, "lat": 1.2516825, "lon": 42.5775654, "tags": {"name": "Bu'aale \u0628\u0648\u0623\u0644", "name:ar": "\u0628\u0648\u0623\u0644", "name:de": "Bu'aale", "name:en": "Bu'aale", "name:es": "Bu'aale", "name:fr": "Bu'aale", "name:ko": "\ubd80\uc54c\ub808", "name:ru": "\u0411\u0443\u0430\u043b\u0435", "place": "city", "wikidata": "Q997314", "wikipedia": "en:Bu'ale"}}, {"type": "node", "id": 314263245, "lat": 2.058068, "lon": 45.3083806}, {"type": "node", "id": 348404564, "lat": 3.8928602, "lon": 41.8454774}, {"type": "node", "id": 348404568, "lat": 3.158622, "lon": 41.3244709}, {"type": "node", "id": 348404572, "lat": 3.1412366, "lon": 41.3120527}, {"type": "node", "id": 348404576, "lat": 2.8282984, "lon": 40.98918}, {"type": "node", "id": 348404585, "lat": -0.833591, "lon": 40.99344}, {"type": "node", "id": 348404589, "lat": -1.5985737, "lon": 41.5589115}, {"type": "node", "id": 348404623, "lat": 4.9257994, "lon": 44.5899236}, {"type": "node", "id": 348404625, "lat": 4.9257994, "lon": 44.5491729}, {"type": "node", "id": 348404628, "lat": 4.9409624, "lon": 44.3852221}, {"type": "node", "id": 348404630, "lat": 4.942384, "lon": 44.2018436}, {"type": "node", "id": 348404632, "lat": 4.9504394, "lon": 44.1539852}, {"type": "node", "id": 348404634, "lat": 4.9471224, "lon": 44.1227113}, {"type": "node", "id": 348404636, "lat": 4.9400147, "lon": 44.0786436}, {"type": "node", "id": 348404638, "lat": 4.9433317, "lon": 44.0317329}, {"type": "node", "id": 348404641, "lat": 4.9253255, "lon": 43.9379113}, {"type": "node", "id": 348404643, "lat": 4.9163224, "lon": 43.8900529}, {"type": "node", "id": 348404645, "lat": 4.9087409, "lon": 43.8455113}, {"type": "node", "id": 348404647, "lat": 4.9021071, "lon": 43.8090252}, {"type": "node", "id": 348404650, "lat": 4.8888394, "lon": 43.7895975}, {"type": "node", "id": 348404652, "lat": 4.8864701, "lon": 43.7559544}, {"type": "node", "id": 348404654, "lat": 4.8665686, "lon": 43.6825083}, {"type": "node", "id": 348404657, "lat": 4.8424024, "lon": 43.5811052}, {"type": "node", "id": 348404660, "lat": 4.8357686, "lon": 43.5702067}, {"type": "node", "id": 348404662, "lat": 4.8352947, "lon": 43.5522006}, {"type": "node", "id": 348404666, "lat": 4.794544, "lon": 43.4346867}, {"type": "node", "id": 348404668, "lat": 4.6950363, "lon": 43.2318806}, {"type": "node", "id": 348404670, "lat": 4.6523901, "lon": 43.1570129}, {"type": "node", "id": 348404675, "lat": 4.6263286, "lon": 43.1153144}, {"type": "node", "id": 348404678, "lat": 4.6021624, "lon": 43.0793021}, {"type": "node", "id": 348404681, "lat": 4.572784, "lon": 43.0451852}, {"type": "node", "id": 348404683, "lat": 4.5590424, "lon": 43.0347606}, {"type": "node", "id": 348404685, "lat": 4.5415101, "lon": 43.0257575}, {"type": "node", "id": 348404687, "lat": 4.5206609, "lon": 43.0200713}, {"type": "node", "id": 348404690, "lat": 4.4832271, "lon": 43.0124898}, {"type": "node", "id": 348404692, "lat": 4.4681208, "lon": 43.007467}, {"type": "node", "id": 348404694, "lat": 4.4496219, "lon": 42.9965496}, {"type": "node", "id": 348404696, "lat": 4.4359751, "lon": 42.9895746}, {"type": "node", "id": 348404697, "lat": 4.4220251, "lon": 42.9804767}, {"type": "node", "id": 348404698, "lat": 4.4029196, "lon": 42.9692561}, {"type": "node", "id": 348404699, "lat": 4.3804783, "lon": 42.9519702}, {"type": "node", "id": 348404702, "lat": 4.347726, "lon": 42.9249799}, {"type": "node", "id": 348404703, "lat": 4.3180064, "lon": 42.8973831}, {"type": "node", "id": 348404704, "lat": 4.3058759, "lon": 42.8828265}, {"type": "node", "id": 348404705, "lat": 4.2876802, "lon": 42.8600819}, {"type": "node", "id": 348404706, "lat": 4.2797954, "lon": 42.848558}, {"type": "node", "id": 348404707, "lat": 4.2710008, "lon": 42.8324851}, {"type": "node", "id": 348404709, "lat": 4.2667552, "lon": 42.8249036}, {"type": "node", "id": 348404711, "lat": 4.2652389, "lon": 42.8155025}, {"type": "node", "id": 348404713, "lat": 4.2646324, "lon": 42.7606121}, {"type": "node", "id": 348404715, "lat": 4.2643291, "lon": 42.7357447}, {"type": "node", "id": 348404717, "lat": 4.2628128, "lon": 42.7184588}, {"type": "node", "id": 348404720, "lat": 4.2603867, "lon": 42.7029924}, {"type": "node", "id": 348404722, "lat": 4.2543215, "lon": 42.6829772}, {"type": "node", "id": 348404724, "lat": 4.2494693, "lon": 42.6690272}, {"type": "node", "id": 348404727, "lat": 4.2349127, "lon": 42.637488}, {"type": "node", "id": 348404729, "lat": 4.2158072, "lon": 42.5868433}, {"type": "node", "id": 348404731, "lat": 4.2121681, "lon": 42.5719835}, {"type": "node", "id": 348404733, "lat": 4.2067094, "lon": 42.554091}, {"type": "node", "id": 348404735, "lat": 4.2024637, "lon": 42.5255844}, {"type": "node", "id": 348404737, "lat": 4.2030703, "lon": 42.494955}, {"type": "node", "id": 348404739, "lat": 4.202767, "lon": 42.4746365}, {"type": "node", "id": 348404741, "lat": 4.1930626, "lon": 42.4042798}, {"type": "node", "id": 348404743, "lat": 4.1894235, "lon": 42.3700113}, {"type": "node", "id": 348404746, "lat": 4.1821452, "lon": 42.2517393}, {"type": "node", "id": 348404748, "lat": 4.1791126, "lon": 42.1941196}, {"type": "node", "id": 348404750, "lat": 4.1791126, "lon": 42.0873715}, {"type": "node", "id": 348404753, "lat": 4.1750392, "lon": 42.0796541}, {"type": "node", "id": 348404755, "lat": 4.1677415, "lon": 42.0689405}, {"type": "node", "id": 348404757, "lat": 4.1612202, "lon": 42.0607112}, {"type": "node", "id": 348404759, "lat": 4.1506618, "lon": 42.0504634}, {"type": "node", "id": 348404762, "lat": 4.1310978, "lon": 42.0343153}, {"type": "node", "id": 348404764, "lat": 4.101286, "lon": 42.008851}, {"type": "node", "id": 348404765, "lat": 4.0935225, "lon": 42.0003112}, {"type": "node", "id": 348404766, "lat": 4.0953857, "lon": 41.978884}, {"type": "node", "id": 348404767, "lat": 4.0812562, "lon": 41.9743811}, {"type": "node", "id": 348404768, "lat": 4.0795482, "lon": 41.9717415}, {"type": "node", "id": 348404769, "lat": 4.0798945, "lon": 41.9668584}, {"type": "node", "id": 348404770, "lat": 4.0554814, "lon": 41.9462773}, {"type": "node", "id": 348404774, "lat": 4.0444572, "lon": 41.9459667}, {"type": "node", "id": 348404776, "lat": 4.0281539, "lon": 41.9487616}, {"type": "node", "id": 348404777, "lat": 4.0166639, "lon": 41.9430166}, {"type": "node", "id": 348404779, "lat": 4.0022238, "lon": 41.9262475}, {"type": "node", "id": 348404781, "lat": 3.9952522, "lon": 41.9219223}, {"type": "node", "id": 348404783, "lat": 3.9914027, "lon": 41.912052}, {"type": "node", "id": 348404785, "lat": 3.9826897, "lon": 41.9073271}, {"type": "node", "id": 348404788, "lat": 3.9826836, "lon": 41.9067502}, {"type": "node", "id": 348404793, "lat": 3.9362341, "lon": 41.8725241}, {"type": "node", "id": 348404795, "lat": 3.918873, "lon": 41.8574597}, {"type": "node", "id": 348404799, "lat": 3.8735044, "lon": 41.829641}, {"type": "node", "id": 348520903, "lat": 3.5245883, "lon": 41.5749254}, {"type": "node", "id": 348520916, "lat": 3.355146, "lon": 41.4578561}, {"type": "node", "id": 348520932, "lat": 3.715596, "lon": 41.7166407}, {"type": "node", "id": 348520945, "lat": 2.9854537, "lon": 41.1466985}, {"type": "node", "id": 348521017, "lat": 0.9305275, "lon": 40.9946012}, {"type": "node", "id": 348521030, "lat": 0.1819857, "lon": 40.994148}, {"type": "node", "id": 348521059, "lat": -0.9948997, "lon": 41.11281}, {"type": "node", "id": 348521068, "lat": -1.2165809, "lon": 41.2767301}, {"type": "node", "id": 348521080, "lat": -1.4168646, "lon": 41.4250699}, {"type": "node", "id": 357059272, "lat": 0.5163514, "lon": 40.9944436}, {"type": "node", "id": 357060538, "lat": 2.1762583, "lon": 40.9915471}, {"type": "node", "id": 377819849, "lat": 3.9327414, "lon": 41.8705576}, {"type": "node", "id": 1395957416, "lat": 4.16358, "lon": 42.076407, "tags": {"alt_name": "Dolow", "name": "Doolow \u062f\u0648\u0644\u0648", "name:ar": "\u062f\u0648\u0644\u0648", "name:so": "Dooloow", "place": "city", "population": "26800", "wikidata": "Q1017164", "wikipedia": "en:Dolow"}}, {"type": "node", "id": 1404223298, "lat": 4.5384212, "lon": 43.0250009, "tags": {"alt_name": "Yeet", "name": "Yeed", "pcode": "NB-3813-L23-003", "place": "town", "source": "UNDP - 2006, UNDP - 1997, FSAU", "wikidata": "Q8051110"}}, {"type": "node", "id": 1404225468, "lat": 3.79999, "lon": 42.54459, "tags": {"alt_name": "Luuk;Luq;Lugh;Lugh Ferrandi;Luuq-Ganaane;Luuq Ganaane", "name": "Luuq \u0644\u0648\u0642", "name:ar": "\u0644\u0648\u0642", "pcode": "NA-3801-E12-002", "place": "city", "source": "UNDP - 1997, FSAU", "wikidata": "Q1878274", "wikipedia": "so:Luuq"}}, {"type": "node", "id": 1404227318, "lat": 3.80925, "lon": 43.247089, "tags": {"alt_name": "Wajid", "name": "Waajid \u0648\u0627\u0627\u062c\u064a\u062f", "name:ar": "\u0648\u0627\u0627\u062c\u064a\u062f", "name:ca": "Wajid", "name:de": "Wajid", "name:en": "Wajid", "name:fr": "Wajid", "name:it": "Uegit", "name:ja": "\u30ef\u30b8\u30c9", "name:pl": "Waajid", "name:ro": "Wajid", "name:ur": "\u0648\u0627\u062c\u062f", "name:zu": "Wajid", "pcode": "NA-3801-E28-001", "place": "town", "source": "UNDP - 1997, FSAU", "wikidata": "Q2064657", "wikipedia": "so:Waajid"}}, {"type": "node", "id": 1404233530, "lat": 3.3280189, "lon": 42.219898, "tags": {"alt_name": "Garboharey;Garbaharey, Garba Hare", "name": "Garbahaarey \u062c\u0631\u0628\u0647\u0627\u0631\u064a", "name:ar": "\u062c\u0631\u0628\u0647\u0627\u0631\u064a", "name:en": "Garbaharey", "name:ru": "\u0413\u0430\u0440\u0431\u0430\u0445\u0430\u0440\u0440\u0435\u0439", "pcode": "NA-3801-S05-001", "place": "city", "source": "UNDP - 1997, FSAU", "wikidata": "Q1017167", "wikipedia": "en:Garbahare"}}, {"type": "node", "id": 1406047774, "lat": -0.1996903, "lon": 40.9933795}, {"type": "node", "id": 1406049997, "lat": 0.92, "lon": 43.3499985}, {"type": "node", "id": 1406050012, "lat": 0.9354485, "lon": 43.3387604}, {"type": "node", "id": 1406050094, "lat": 1.03, "lon": 43.2700005}, {"type": "node", "id": 1406050096, "lat": 1.044656, "lon": 43.2601204}, {"type": "node", "id": 1406050160, "lat": 1.2307847, "lon": 40.9932585}, {"type": "node", "id": 1406050169, "lat": 1.26, "lon": 41.4199982}, {"type": "node", "id": 1406050240, "lat": 1.46, "lon": 42.9799995}, {"type": "node", "id": 1406050243, "lat": 1.480714, "lon": 42.9523811}, {"type": "node", "id": 1406050267, "lat": 1.52, "lon": 42.9000015}, {"type": "node", "id": 1406050441, "lat": 1.88, "lon": 42.5200005}, {"type": "node", "id": 1406050515, "lat": 1.9400001, "lon": 41.6399994}, {"type": "node", "id": 1406050521, "lat": 1.95, "lon": 42.4000015}, {"type": "node", "id": 1406050558, "lat": 1.9742133, "lon": 45.2319257}, {"type": "node", "id": 1406050562, "lat": 1.9743139, "lon": 45.2309285}, {"type": "node", "id": 1406050579, "lat": 1.9757111, "lon": 45.2301135}, {"type": "node", "id": 1406050583, "lat": 1.9761449, "lon": 45.2301123}, {"type": "node", "id": 1406054401, "lat": 2.0185568, "lon": 45.229997}, {"type": "node", "id": 1406055085, "lat": 2.0449576, "lon": 45.2826701}, {"type": "node", "id": 1406055165, "lat": 2.0515623, "lon": 45.2782919}, {"type": "node", "id": 1406055238, "lat": 2.0546922, "lon": 45.3016666}, {"type": "node", "id": 1406055244, "lat": 2.0550555, "lon": 45.3008944}, {"type": "node", "id": 1406055282, "lat": 2.0581991, "lon": 45.296703}, {"type": "node", "id": 1406055297, "lat": 2.0594881, "lon": 45.3109957}, {"type": "node", "id": 1406055301, "lat": 2.0594142, "lon": 45.3108815}, {"type": "node", "id": 1406055305, "lat": 2.0596252, "lon": 45.3112531}, {"type": "node", "id": 1406055307, "lat": 2.0595959, "lon": 45.2697926}, {"type": "node", "id": 1406055343, "lat": 2.0636709, "lon": 45.264204}, {"type": "node", "id": 1406055347, "lat": 2.0640533, "lon": 45.3201409}, {"type": "node", "id": 1406055349, "lat": 2.0639757, "lon": 45.3199344}, {"type": "node", "id": 1406055362, "lat": 2.0646023, "lon": 45.2618755}, {"type": "node", "id": 1406055375, "lat": 2.0656501, "lon": 45.2583826}, {"type": "node", "id": 1406055443, "lat": 2.0694923, "lon": 45.2525612}, {"type": "node", "id": 1406055444, "lat": 2.0688975, "lon": 45.2507287}, {"type": "node", "id": 1406055471, "lat": 2.0720976, "lon": 45.3364942}, {"type": "node", "id": 1406055473, "lat": 2.072615, "lon": 45.3364923}, {"type": "node", "id": 1406055476, "lat": 2.072534, "lon": 45.3368434}, {"type": "node", "id": 1406055533, "lat": 2.0791562, "lon": 45.251878}, {"type": "node", "id": 1406055543, "lat": 2.0803205, "lon": 45.253508}, {"type": "node", "id": 1406055556, "lat": 2.081252, "lon": 45.2552544}, {"type": "node", "id": 1406055567, "lat": 2.0828819, "lon": 45.254323}, {"type": "node", "id": 1406055575, "lat": 2.0838134, "lon": 45.2537409}, {"type": "node", "id": 1406055577, "lat": 2.0849777, "lon": 45.2547887}, {"type": "node", "id": 1406055580, "lat": 2.0862584, "lon": 45.2550216}, {"type": "node", "id": 1406055584, "lat": 2.0863769, "lon": 45.3634401}, {"type": "node", "id": 1406055597, "lat": 2.0875391, "lon": 45.255953}, {"type": "node", "id": 1406055601, "lat": 2.0877149, "lon": 45.3643026}, {"type": "node", "id": 1406055605, "lat": 2.0890527, "lon": 45.2568844}, {"type": "node", "id": 1406055609, "lat": 2.0910319, "lon": 45.2570009}, {"type": "node", "id": 1406055612, "lat": 2.0911926, "lon": 45.2569205}, {"type": "node", "id": 1406055615, "lat": 2.0912648, "lon": 45.2568844}, {"type": "node", "id": 1406055628, "lat": 2.0947577, "lon": 45.288553}, {"type": "node", "id": 1406055636, "lat": 2.0967369, "lon": 45.287738}, {"type": "node", "id": 1406055647, "lat": 2.0970862, "lon": 45.281218}, {"type": "node", "id": 1406055649, "lat": 2.0990467, "lon": 45.2865831}, {"type": "node", "id": 1406055652, "lat": 2.0992984, "lon": 45.2864573}, {"type": "node", "id": 1406055658, "lat": 2.0998235, "lon": 45.3698911}, {"type": "node", "id": 1406055698, "lat": 2.1800001, "lon": 45.3300018}, {"type": "node", "id": 1406055730, "lat": 2.2309749, "lon": 45.3309288}, {"type": "node", "id": 1406055785, "lat": 2.3099944, "lon": 40.9903722}, {"type": "node", "id": 1406055883, "lat": 2.5699999, "lon": 42.5099983}, {"type": "node", "id": 1406055911, "lat": 2.5988059, "lon": 42.5150795}, {"type": "node", "id": 1406055922, "lat": 2.6491621, "lon": 45.3386803}, {"type": "node", "id": 1406055933, "lat": 2.652148, "lon": 45.3387413}, {"type": "node", "id": 1406055937, "lat": 2.6551349, "lon": 45.3387909}, {"type": "node", "id": 1406055940, "lat": 2.658123, "lon": 45.3388481}, {"type": "node", "id": 1406055942, "lat": 2.661109, "lon": 45.3389091}, {"type": "node", "id": 1406055964, "lat": 2.72, "lon": 45.3400002}, {"type": "node", "id": 1406055969, "lat": 2.73, "lon": 45.3300018}, {"type": "node", "id": 1406055978, "lat": 2.7306199, "lon": 45.3326988}, {"type": "node", "id": 1406055984, "lat": 2.74, "lon": 42.5400009}, {"type": "node", "id": 1406055990, "lat": 2.749428, "lon": 42.5417099}, {"type": "node", "id": 1406056004, "lat": 2.7692809, "lon": 45.3061104}, {"type": "node", "id": 1406056060, "lat": 3.04, "lon": 42.9300003}, {"type": "node", "id": 1406056062, "lat": 3.04, "lon": 45.1199989}, {"type": "node", "id": 1406056066, "lat": 3.0599999, "lon": 43.0999985}, {"type": "node", "id": 1406056071, "lat": 3.0629511, "lon": 42.6775398}, {"type": "node", "id": 1406056073, "lat": 3.0699999, "lon": 42.5999985}, {"type": "node", "id": 1406056074, "lat": 3.0799999, "lon": 43.0999985}, {"type": "node", "id": 1406056079, "lat": 3.1398136, "lon": 41.3105422}, {"type": "node", "id": 1406056102, "lat": 3.23, "lon": 43.0999985}, {"type": "node", "id": 1406056104, "lat": 3.25, "lon": 44.6599998}, {"type": "node", "id": 1406056107, "lat": 3.25, "lon": 45.0699997}, {"type": "node", "id": 1406056112, "lat": 3.255811, "lon": 43.1011696}, {"type": "node", "id": 1406056115, "lat": 3.26, "lon": 44.4099998}, {"type": "node", "id": 1406056121, "lat": 3.263042, "lon": 44.4708519}, {"type": "node", "id": 1406056124, "lat": 3.2631831, "lon": 44.8788414}, {"type": "node", "id": 1406056126, "lat": 3.27, "lon": 44.6100006}, {"type": "node", "id": 1406056129, "lat": 3.27, "lon": 44.7799988}, {"type": "node", "id": 1406056138, "lat": 3.307724, "lon": 44.3324509}, {"type": "node", "id": 1406056149, "lat": 3.3399999, "lon": 44.2799988}, {"type": "node", "id": 1406056152, "lat": 3.3499999, "lon": 42.8499985}, {"type": "node", "id": 1406056155, "lat": 3.3900001, "lon": 44.3100014}, {"type": "node", "id": 1406056165, "lat": 3.4400001, "lon": 42.6399994}, {"type": "node", "id": 1406056188, "lat": 3.5696051, "lon": 44.7730293}, {"type": "node", "id": 1406056190, "lat": 3.5699999, "lon": 43.4099998}, {"type": "node", "id": 1406056195, "lat": 3.5699999, "lon": 44.3100014}, {"type": "node", "id": 1406056214, "lat": 3.6099999, "lon": 43.5800018}, {"type": "node", "id": 1406056215, "lat": 3.6099999, "lon": 44.2900009}, {"type": "node", "id": 1406056230, "lat": 3.6700001, "lon": 43.1199989}, {"type": "node", "id": 1406056240, "lat": 3.6800001, "lon": 42.0400009}, {"type": "node", "id": 1406056242, "lat": 3.7, "lon": 44.7700005}, {"type": "node", "id": 1406056244, "lat": 3.72, "lon": 43.6800003}, {"type": "node", "id": 1406056256, "lat": 3.79, "lon": 42.2299995}, {"type": "node", "id": 1406056257, "lat": 3.8099999, "lon": 42.0999985}, {"type": "node", "id": 1406056264, "lat": 3.8499999, "lon": 43.1399994}, {"type": "node", "id": 1406056266, "lat": 3.8499999, "lon": 43.75}, {"type": "node", "id": 1406056270, "lat": 3.8499999, "lon": 44.1800003}, {"type": "node", "id": 1406056271, "lat": 3.8599999, "lon": 44.7999992}, {"type": "node", "id": 1406056275, "lat": 3.8800001, "lon": 43.7900009}, {"type": "node", "id": 1406056278, "lat": 3.8830769, "lon": 43.7969208}, {"type": "node", "id": 1406056281, "lat": 3.9105664, "lon": 41.8587037}, {"type": "node", "id": 1406056283, "lat": 3.9200001, "lon": 43.7599983}, {"type": "node", "id": 1406056286, "lat": 3.9200001, "lon": 43.8800011}, {"type": "node", "id": 1406056287, "lat": 3.9200001, "lon": 43.9500008}, {"type": "node", "id": 1406056288, "lat": 3.9300001, "lon": 43.0999985}, {"type": "node", "id": 1406056290, "lat": 3.9462531, "lon": 43.090519}, {"type": "node", "id": 1406056302, "lat": 4.0500002, "lon": 43.6300011}, {"type": "node", "id": 1406056303, "lat": 4.0700002, "lon": 44.75}, {"type": "node", "id": 1406056304, "lat": 4.0762959, "lon": 44.7486992}, {"type": "node", "id": 1406056319, "lat": 4.1927315, "lon": 42.4011624}, {"type": "node", "id": 1406056338, "lat": 4.29, "lon": 42.8899994}, {"type": "node", "id": 1406056341, "lat": 4.3069829, "lon": 42.8841549}, {"type": "node", "id": 1406056369, "lat": 4.4099998, "lon": 44.6800003}, {"type": "node", "id": 1406056377, "lat": 4.4299998, "lon": 44.676609}, {"type": "node", "id": 1406056384, "lat": 4.48, "lon": 43.2799988}, {"type": "node", "id": 1406056407, "lat": 4.633388, "lon": 43.1266094}, {"type": "node", "id": 1406056424, "lat": 4.8703122, "lon": 44.601841}, {"type": "node", "id": 1406056430, "lat": 4.9319746, "lon": 44.5895692}, {"type": "node", "id": 1406152694, "lat": 1.9740665, "lon": 45.2332664}, {"type": "node", "id": 1406514988, "lat": 2.0626059, "lon": 45.2957206}, {"type": "node", "id": 1699639864, "lat": -0.3743405, "lon": 42.7983767}, {"type": "node", "id": 1699639867, "lat": -0.4258131, "lon": 42.770365}, {"type": "node", "id": 1699639870, "lat": -0.6304797, "lon": 42.6206784}, {"type": "node", "id": 1699639871, "lat": -0.8535777, "lon": 42.4415768}, {"type": "node", "id": 1699639872, "lat": -1.0921596, "lon": 42.2435511}, {"type": "node", "id": 1699639873, "lat": -1.3155361, "lon": 42.063424}, {"type": "node", "id": 1699639875, "lat": -1.4638518, "lon": 41.9473452}, {"type": "node", "id": 1699639892, "lat": -1.6748551, "lon": 41.8097712}, {"type": "node", "id": 1699639895, "lat": -1.7770316, "lon": 41.7410207}, {"type": "node", "id": 1699639898, "lat": -1.801007, "lon": 41.7207156}, {"type": "node", "id": 1699640044, "lat": 0.1529078, "lon": 43.3020598}, {"type": "node", "id": 1699640045, "lat": 0.4793006, "lon": 43.6037395}, {"type": "node", "id": 1699640046, "lat": 0.984148, "lon": 44.1982834}, {"type": "node", "id": 1699640055, "lat": 1.4692169, "lon": 44.7742761}, {"type": "node", "id": 1699640058, "lat": 1.7142782, "lon": 45.1586965}, {"type": "node", "id": 1994053672, "lat": 0.2055511, "lon": 43.3488687}, {"type": "node", "id": 1994053675, "lat": 1.2895722, "lon": 44.5391602}, {"type": "node", "id": 1994053679, "lat": 1.7430576, "lon": 45.2091149}, {"type": "node", "id": 2275588565, "lat": 0.4089016, "lon": 40.9945937}, {"type": "node", "id": 2510206687, "lat": 4.1632355, "lon": 42.0630513}, {"type": "node", "id": 2533888087, "lat": 3.9267335, "lon": 41.8646962}, {"type": "node", "id": 2544755345, "lat": 0.4613428, "lon": 40.99466}, {"type": "node", "id": 2662892716, "lat": -1.6620659, "lon": 41.5593803}, {"type": "node", "id": 2672071006, "lat": 0.4091151, "lon": 40.9945892}, {"type": "node", "id": 2672071010, "lat": 0.4252811, "lon": 40.9946731}, {"type": "node", "id": 2672071012, "lat": 0.4395506, "lon": 40.9945798}, {"type": "node", "id": 2672071014, "lat": 0.4466644, "lon": 40.9945893}, {"type": "node", "id": 2672071016, "lat": 0.4514944, "lon": 40.9946001}, {"type": "node", "id": 2672071018, "lat": 0.4565404, "lon": 40.9949131}, {"type": "node", "id": 2672071019, "lat": 0.4579111, "lon": 40.9948969}, {"type": "node", "id": 3134138914, "lat": 1.0552856, "lon": 44.2817902}, {"type": "node", "id": 3134138915, "lat": 1.0732239, "lon": 44.2954378}, {"type": "node", "id": 3134138916, "lat": 1.0885433, "lon": 44.3040031}, {"type": "node", "id": 3134138917, "lat": 1.0914013, "lon": 44.309642}, {"type": "node", "id": 3134138918, "lat": 1.10928, "lon": 44.3345369}, {"type": "node", "id": 3134138919, "lat": 1.1307744, "lon": 44.3564289}, {"type": "node", "id": 3134138920, "lat": 1.154584, "lon": 44.377111}, {"type": "node", "id": 3134138921, "lat": 1.1580272, "lon": 44.3791399}, {"type": "node", "id": 3134138922, "lat": 1.1758644, "lon": 44.3999275}, {"type": "node", "id": 3134138923, "lat": 1.1952724, "lon": 44.4284769}, {"type": "node", "id": 3134138924, "lat": 1.2231609, "lon": 44.4563639}, {"type": "node", "id": 3134138925, "lat": 1.2313251, "lon": 44.4620169}, {"type": "node", "id": 3134138926, "lat": 1.2453328, "lon": 44.4838481}, {"type": "node", "id": 3134138927, "lat": 1.2785284, "lon": 44.5222412}, {"type": "node", "id": 3134138928, "lat": 1.3857399, "lon": 44.661028}, {"type": "node", "id": 3134138958, "lat": -0.0302006, "lon": 43.1329249}, {"type": "node", "id": 3134138959, "lat": -0.102117, "lon": 43.0686737}, {"type": "node", "id": 3134138960, "lat": -0.1476108, "lon": 43.0259781}, {"type": "node", "id": 3134138961, "lat": -0.291591, "lon": 42.8821367}, {"type": "node", "id": 3134138962, "lat": -0.3315795, "lon": 42.8397009}, {"type": "node", "id": 3134138963, "lat": -0.3896709, "lon": 42.7812538}, {"type": "node", "id": 3134138964, "lat": -0.4010153, "lon": 42.7785436}, {"type": "node", "id": 3134138965, "lat": -0.460542, "lon": 42.7519284}, {"type": "node", "id": 3134138966, "lat": -0.4909826, "lon": 42.7271167}, {"type": "node", "id": 3134138967, "lat": -0.4986204, "lon": 42.7181423}, {"type": "node", "id": 3134138968, "lat": -0.5039136, "lon": 42.7144795}, {"type": "node", "id": 3134138969, "lat": -0.5239763, "lon": 42.6966366}, {"type": "node", "id": 3134138970, "lat": -0.5348834, "lon": 42.6851029}, {"type": "node", "id": 3134138971, "lat": -0.5581372, "lon": 42.6708163}, {"type": "node", "id": 3134138972, "lat": -0.5744282, "lon": 42.657599}, {"type": "node", "id": 3134138973, "lat": -0.5847502, "lon": 42.6472013}, {"type": "node", "id": 3134138974, "lat": -0.5893607, "lon": 42.6447511}, {"type": "node", "id": 3134138975, "lat": -0.6063835, "lon": 42.6308684}, {"type": "node", "id": 3134138976, "lat": -0.6581622, "lon": 42.6040134}, {"type": "node", "id": 3134138977, "lat": -0.6827902, "lon": 42.583148}, {"type": "node", "id": 3134138978, "lat": -0.704258, "lon": 42.5593988}, {"type": "node", "id": 3134138979, "lat": -0.7237729, "lon": 42.5288305}, {"type": "node", "id": 3134138980, "lat": -0.7508412, "lon": 42.513375}, {"type": "node", "id": 3134138981, "lat": -0.7714955, "lon": 42.4994426}, {"type": "node", "id": 3134138982, "lat": -0.7894979, "lon": 42.4910491}, {"type": "node", "id": 3134138983, "lat": -0.8191112, "lon": 42.4704702}, {"type": "node", "id": 3134138984, "lat": -0.8735636, "lon": 42.4230037}, {"type": "node", "id": 3134138985, "lat": -0.8806888, "lon": 42.4186029}, {"type": "node", "id": 3134138986, "lat": -0.9167871, "lon": 42.389188}, {"type": "node", "id": 3134138987, "lat": -0.9274878, "lon": 42.3816125}, {"type": "node", "id": 3134138988, "lat": -0.9493068, "lon": 42.3623779}, {"type": "node", "id": 3134138989, "lat": -0.9603586, "lon": 42.3505487}, {"type": "node", "id": 3134138990, "lat": -0.9852124, "lon": 42.3316642}, {"type": "node", "id": 3134138991, "lat": -1.0036577, "lon": 42.3123}, {"type": "node", "id": 3134138992, "lat": -1.0115727, "lon": 42.3069849}, {"type": "node", "id": 3134138993, "lat": -1.0332829, "lon": 42.2892346}, {"type": "node", "id": 3134138994, "lat": -1.0438581, "lon": 42.2840944}, {"type": "node", "id": 3134138995, "lat": -1.0780718, "lon": 42.2579708}, {"type": "node", "id": 3134138996, "lat": -1.1140812, "lon": 42.225889}, {"type": "node", "id": 3134138997, "lat": -1.1383789, "lon": 42.1979194}, {"type": "node", "id": 3134138998, "lat": -1.1482949, "lon": 42.1913138}, {"type": "node", "id": 3134138999, "lat": -1.1651374, "lon": 42.1770185}, {"type": "node", "id": 3134139000, "lat": -1.2025626, "lon": 42.1553223}, {"type": "node", "id": 3134139001, "lat": -1.2270581, "lon": 42.1340897}, {"type": "node", "id": 3134139002, "lat": -1.2366564, "lon": 42.1239721}, {"type": "node", "id": 3134139003, "lat": -1.2599148, "lon": 42.1095411}, {"type": "node", "id": 3134139004, "lat": -1.2886062, "lon": 42.08962}, {"type": "node", "id": 3134139005, "lat": -1.3391666, "lon": 42.0456024}, {"type": "node", "id": 3134139006, "lat": -1.3522879, "lon": 42.0336773}, {"type": "node", "id": 3134139007, "lat": -1.370489, "lon": 42.0150351}, {"type": "node", "id": 3134139008, "lat": -1.3842227, "lon": 41.9964502}, {"type": "node", "id": 3134139009, "lat": -1.3938478, "lon": 41.9906057}, {"type": "node", "id": 3134139010, "lat": -1.4146715, "lon": 41.9740157}, {"type": "node", "id": 3134139011, "lat": -1.4315906, "lon": 41.9670743}, {"type": "node", "id": 3134139012, "lat": -1.4845895, "lon": 41.9315536}, {"type": "node", "id": 3134139013, "lat": -1.496994, "lon": 41.9240361}, {"type": "node", "id": 3134139014, "lat": -1.5137406, "lon": 41.9094993}, {"type": "node", "id": 3134139015, "lat": -1.5266701, "lon": 41.9012037}, {"type": "node", "id": 3134139016, "lat": -1.5315684, "lon": 41.8967717}, {"type": "node", "id": 3134139017, "lat": -1.5708955, "lon": 41.8781081}, {"type": "node", "id": 3134139018, "lat": -1.5863346, "lon": 41.8687495}, {"type": "node", "id": 3134139019, "lat": -1.6130448, "lon": 41.8476352}, {"type": "node", "id": 3134139020, "lat": -1.6230701, "lon": 41.836471}, {"type": "node", "id": 3134139021, "lat": -1.6356211, "lon": 41.8322675}, {"type": "node", "id": 3134139022, "lat": -1.6624703, "lon": 41.818674}, {"type": "node", "id": 3134139023, "lat": -1.7042362, "lon": 41.7925688}, {"type": "node", "id": 3134139024, "lat": -1.7391133, "lon": 41.7677781}, {"type": "node", "id": 3134139025, "lat": -1.7520917, "lon": 41.7597129}, {"type": "node", "id": 3134139026, "lat": -1.8031969, "lon": 41.718166}, {"type": "node", "id": 3134139027, "lat": 0.0976963, "lon": 43.2525896}, {"type": "node", "id": 3134139028, "lat": 0.1281505, "lon": 43.278178}, {"type": "node", "id": 3134140429, "lat": 0.2144481, "lon": 43.3569738}, {"type": "node", "id": 3134140430, "lat": 0.4016828, "lon": 43.5275444}, {"type": "node", "id": 3134140431, "lat": 0.5368891, "lon": 43.6633753}, {"type": "node", "id": 3134140432, "lat": 0.5580867, "lon": 43.6853266}, {"type": "node", "id": 3134140433, "lat": 0.621891, "lon": 43.7597508}, {"type": "node", "id": 3134140434, "lat": 0.6350084, "lon": 43.771048}, {"type": "node", "id": 3134140435, "lat": 0.6581158, "lon": 43.7958649}, {"type": "node", "id": 3134140436, "lat": 0.6772029, "lon": 43.8204069}, {"type": "node", "id": 3134140437, "lat": 0.6881842, "lon": 43.836988}, {"type": "node", "id": 3134140438, "lat": 0.7035839, "lon": 43.8543935}, {"type": "node", "id": 3134140439, "lat": 0.7262778, "lon": 43.8846245}, {"type": "node", "id": 3134140440, "lat": 0.7531711, "lon": 43.9094273}, {"type": "node", "id": 3134140441, "lat": 0.7595747, "lon": 43.9134111}, {"type": "node", "id": 3134140442, "lat": 0.7757202, "lon": 43.9357091}, {"type": "node", "id": 3134140443, "lat": 0.8047884, "lon": 43.969794}, {"type": "node", "id": 3134140444, "lat": 0.828963, "lon": 44.0051916}, {"type": "node", "id": 3134140445, "lat": 0.837765, "lon": 44.0162414}, {"type": "node", "id": 3134140446, "lat": 0.8428017, "lon": 44.0284716}, {"type": "node", "id": 3134140447, "lat": 0.8592337, "lon": 44.0553419}, {"type": "node", "id": 3134140448, "lat": 0.8797072, "lon": 44.0793178}, {"type": "node", "id": 3134140449, "lat": 0.9040445, "lon": 44.1000443}, {"type": "node", "id": 3134140450, "lat": 0.9137041, "lon": 44.1204865}, {"type": "node", "id": 3134140451, "lat": 0.9325525, "lon": 44.1476155}, {"type": "node", "id": 3134140452, "lat": 0.9645741, "lon": 44.1815457}, {"type": "node", "id": 3134140453, "lat": 1.0007588, "lon": 44.2088393}, {"type": "node", "id": 3134140454, "lat": 1.0053512, "lon": 44.2200021}, {"type": "node", "id": 3134140455, "lat": 1.0235227, "lon": 44.2488797}, {"type": "node", "id": 3134140456, "lat": 1.0307788, "lon": 44.257213}, {"type": "node", "id": 3134140457, "lat": 1.0463683, "lon": 44.2742711}, {"type": "node", "id": 3134140529, "lat": 1.4111644, "lon": 44.6932479}, {"type": "node", "id": 3134140530, "lat": 1.4229616, "lon": 44.710185}, {"type": "node", "id": 3134140531, "lat": 1.4311974, "lon": 44.72543}, {"type": "node", "id": 3134140532, "lat": 1.440204, "lon": 44.7389545}, {"type": "node", "id": 3134140533, "lat": 1.4875444, "lon": 44.8052683}, {"type": "node", "id": 3134140534, "lat": 1.5016899, "lon": 44.8234343}, {"type": "node", "id": 3134140535, "lat": 1.5201202, "lon": 44.8543652}, {"type": "node", "id": 3134140536, "lat": 1.5394269, "lon": 44.8799743}, {"type": "node", "id": 3134140537, "lat": 1.5481899, "lon": 44.8887858}, {"type": "node", "id": 3134140538, "lat": 1.5679379, "lon": 44.9183218}, {"type": "node", "id": 3134140539, "lat": 1.594241, "lon": 44.9617702}, {"type": "node", "id": 3134140540, "lat": 1.6124538, "lon": 44.9878644}, {"type": "node", "id": 3134140541, "lat": 1.6360766, "lon": 45.0308857}, {"type": "node", "id": 3134140542, "lat": 1.6727982, "lon": 45.0915262}, {"type": "node", "id": 3134140543, "lat": 1.675841, "lon": 45.0991504}, {"type": "node", "id": 3134140544, "lat": 1.684487, "lon": 45.1144865}, {"type": "node", "id": 3134140545, "lat": 1.6957003, "lon": 45.1310623}, {"type": "node", "id": 3134140546, "lat": 1.7104838, "lon": 45.1499669}, {"type": "node", "id": 3134140547, "lat": 1.7346361, "lon": 45.1927398}, {"type": "node", "id": 3134140548, "lat": 1.7498655, "lon": 45.2295837}, {"type": "node", "id": 3134140549, "lat": 1.7643263, "lon": 45.2603378}, {"type": "node", "id": 3134140550, "lat": 1.7674376, "lon": 45.2710048}, {"type": "node", "id": 3134140551, "lat": 1.7773102, "lon": 45.2965242}, {"type": "node", "id": 3134140552, "lat": 1.7848321, "lon": 45.3133272}, {"type": "node", "id": 3134140553, "lat": 1.7868639, "lon": 45.3177585}, {"type": "node", "id": 3136498639, "lat": 2.0240681, "lon": 45.2416446}, {"type": "node", "id": 3165622245, "lat": 3.9251192, "lon": 41.8634766}, {"type": "node", "id": 3186821408, "lat": 3.9318505, "lon": 41.8699088}, {"type": "node", "id": 3186821409, "lat": 3.9339675, "lon": 41.871453}, {"type": "node", "id": 3187186592, "lat": 3.9379501, "lon": 41.8736506}, {"type": "node", "id": 3772944993, "lat": -1.3045575, "lon": 41.3418884}, {"type": "node", "id": 3772944998, "lat": -1.3123279, "lon": 41.3476434}, {"type": "node", "id": 3772945012, "lat": -1.3346215, "lon": 41.3641552}, {"type": "node", "id": 3772945025, "lat": -1.3171207, "lon": 41.3511932}, {"type": "node", "id": 3772945035, "lat": -1.3320596, "lon": 41.3622578}, {"type": "node", "id": 3772945056, "lat": -1.3925591, "lon": 41.4070674}, {"type": "node", "id": 3772945058, "lat": -1.3130485, "lon": 41.3481772}, {"type": "node", "id": 3772945072, "lat": -1.3864355, "lon": 41.4025318}, {"type": "node", "id": 4532166688, "lat": 0.2984662, "lon": 40.9943768}, {"type": "node", "id": 4532167215, "lat": 0.3010885, "lon": 40.9943819}, {"type": "node", "id": 5248113440, "lat": 3.1613934, "lon": 41.3263517}, {"type": "node", "id": 5518905650, "lat": 3.9955022, "lon": 41.9216341}, {"type": "node", "id": 5518905651, "lat": 3.9959892, "lon": 41.9204539}, {"type": "node", "id": 5518905652, "lat": 3.9961926, "lon": 41.9198209}, {"type": "node", "id": 5518905653, "lat": 3.9961979, "lon": 41.9191021}, {"type": "node", "id": 5518905654, "lat": 3.9962728, "lon": 41.9184422}, {"type": "node", "id": 5518905655, "lat": 3.9964976, "lon": 41.9167042}, {"type": "node", "id": 5518905656, "lat": 3.9962996, "lon": 41.9172192}, {"type": "node", "id": 5518905657, "lat": 3.996214, "lon": 41.917659}, {"type": "node", "id": 5518905658, "lat": 3.9957538, "lon": 41.9133729}, {"type": "node", "id": 5518905659, "lat": 3.9962889, "lon": 41.9137967}, {"type": "node", "id": 5518905660, "lat": 3.9967224, "lon": 41.9144028}, {"type": "node", "id": 5518905661, "lat": 3.9968347, "lon": 41.9148803}, {"type": "node", "id": 5518905662, "lat": 3.996701, "lon": 41.9155937}, {"type": "node", "id": 5518905663, "lat": 3.9933403, "lon": 41.9126648}, {"type": "node", "id": 5518905664, "lat": 3.9946835, "lon": 41.9129705}, {"type": "node", "id": 5518905665, "lat": 3.9906218, "lon": 41.911844}, {"type": "node", "id": 5518905666, "lat": 3.9899903, "lon": 41.9117153}, {"type": "node", "id": 5518905667, "lat": 3.9881066, "lon": 41.9116133}, {"type": "node", "id": 5518905668, "lat": 3.9886364, "lon": 41.911667}, {"type": "node", "id": 5518905669, "lat": 3.9894177, "lon": 41.9116884}, {"type": "node", "id": 5518905670, "lat": 3.9875072, "lon": 41.9114739}, {"type": "node", "id": 5518905671, "lat": 3.986956, "lon": 41.9112754}, {"type": "node", "id": 5518905722, "lat": 3.9598827, "lon": 41.890912}, {"type": "node", "id": 6395662050, "lat": 2.3402186, "lon": 45.3329537}, {"type": "node", "id": 6395662051, "lat": 2.5448058, "lon": 45.336746}, {"type": "node", "id": 6395662052, "lat": 2.4406678, "lon": 45.3348157}, {"type": "node", "id": 6569461195, "lat": 3.2154979, "lon": 45.078215}, {"type": "node", "id": 6569461775, "lat": 3.1787104, "lon": 45.0869743}, {"type": "node", "id": 7912107911, "lat": 2.0973591, "lon": 45.282196}, {"type": "node", "id": 8396389350, "lat": 3.4989311, "lon": 43.112222}, {"type": "node", "id": 8396389442, "lat": 3.7519523, "lon": 43.1291049}, {"type": "node", "id": 8396389458, "lat": 3.6248384, "lon": 43.2509681}, {"type": "node", "id": 8494615416, "lat": 2.0351923, "lon": 45.2641751}, {"type": "node", "id": 8710929947, "lat": 2.0554398, "lon": 45.300382}, {"type": "node", "id": 8726158678, "lat": 2.0855467, "lon": 45.3616759}, {"type": "node", "id": 8726364793, "lat": 2.0746552, "lon": 45.3408957}, {"type": "node", "id": 8726364794, "lat": 2.0745742, "lon": 45.3407445}, {"type": "node", "id": 8728742356, "lat": 2.0870586, "lon": 45.3637629}, {"type": "node", "id": 8926872109, "lat": 2.066155, "lon": 45.2949247}, {"type": "node", "id": 9431510782, "lat": 2.0859704, "lon": 45.362522}, {"type": "node", "id": 9490093935, "lat": 2.0442503, "lon": 45.2829134}, {"type": "node", "id": 9513675556, "lat": 2.0673169, "lon": 45.3264151}, {"type": "node", "id": 9513675568, "lat": 2.0678733, "lon": 45.3274802}, {"type": "node", "id": 9516000039, "lat": 2.0074317, "lon": 45.2300272}, {"type": "node", "id": 9516000040, "lat": 2.0078017, "lon": 45.2300262}, {"type": "node", "id": 9516000041, "lat": 2.0081127, "lon": 45.2300254}, {"type": "node", "id": 9516000042, "lat": 2.0084291, "lon": 45.2300245}, {"type": "node", "id": 9516000071, "lat": 2.0148732, "lon": 45.230007}, {"type": "node", "id": 9516000072, "lat": 2.0151034, "lon": 45.2300064}, {"type": "node", "id": 9516000075, "lat": 2.0155859, "lon": 45.2300051}, {"type": "node", "id": 9516000076, "lat": 2.0157738, "lon": 45.2300046}, {"type": "node", "id": 9524383206, "lat": 2.0672572, "lon": 45.3262994}, {"type": "node", "id": 9524383209, "lat": 2.0668652, "lon": 45.3255254}, {"type": "node", "id": 9524383210, "lat": 2.0666172, "lon": 45.3250634}, {"type": "node", "id": 9524383211, "lat": 2.066268, "lon": 45.324397}, {"type": "node", "id": 9524401428, "lat": 2.0664318, "lon": 45.3247121}, {"type": "node", "id": 10197384281, "lat": 3.0019075, "lon": 42.5876161}, {"type": "node", "id": 10858937987, "lat": 2.027698, "lon": 45.2490928}, {"type": "node", "id": 11012043039, "lat": -0.120425, "lon": 40.9935391}, {"type": "node", "id": 11012043040, "lat": -0.7948009, "lon": 40.9933761}, {"type": "node", "id": 11057218725, "lat": 2.7349166, "lon": 40.9893948}, {"type": "node", "id": 11057218726, "lat": 3.0120657, "lon": 41.1749439}, {"type": "node", "id": 11057218728, "lat": 3.3836206, "lon": 41.477528}, {"type": "node", "id": 11085449876, "lat": 1.6949165, "lon": 40.9934022}, {"type": "node", "id": 11124891132, "lat": 4.1709853, "lon": 42.0737001}, {"type": "node", "id": 11137843132, "lat": 3.9259408, "lon": 41.8640954}, {"type": "node", "id": 11137843136, "lat": 3.6896872, "lon": 41.6974163}, {"type": "node", "id": 11137843137, "lat": 3.2516128, "lon": 41.3875826}, {"type": "node", "id": 11137843145, "lat": 2.8104187, "lon": 40.9892211}, {"type": "node", "id": 11435472300, "lat": 2.0670583, "lon": 45.3259067}, {"type": "way", "id": 31316551, "nodes": [348404788, 5518905722, 3187186592, 348404793, 3186821409, 377819849, 3186821408, 2533888087, 11137843132], "tags": {"admin_level": "2", "border_type": "nation", "boundary": "administrative", "left:country": "\u0627\u0644\u0635\u0648\u0645\u0627\u0644", "name": "Kenya - \u0627\u0644\u0635\u0648\u0645\u0627\u0644", "name:ar": "\u0643\u064a\u0646\u064a\u0627 - \u0627\u0644\u0635\u0648\u0645\u0627\u0644", "name:en": "Kenya - Somalia", "name:fr": "Kenya - Somalie", "right:country": "Kenya", "right:district": "Mandera", "right:province": "North Eastern", "source": "maplibrary.org"}}, {"type": "way", "id": 31886922, "nodes": [357059272, 2544755345], "tags": {"admin_level": "2", "border_type": "nation", "boundary": "administrative", "name": "Kenya - \u0627\u0644\u0635\u0648\u0645\u0627\u0644", "name:ar": "\u0643\u064a\u0646\u064a\u0627 - \u0627\u0644\u0635\u0648\u0645\u0627\u0644", "name:en": "Kenya - Somalia", "name:fr": "Kenya - Somalie"}}, {"type": "way", "id": 31886935, "nodes": [357060538, 11085449876], "tags": {"admin_level": "2", "border_type": "nation", "boundary": "administrative", "left:country": "\u0627\u0644\u0635\u0648\u0645\u0627\u0644", "name": "Kenya - \u0627\u0644\u0635\u0648\u0645\u0627\u0644", "name:ar": "\u0643\u064a\u0646\u064a\u0627 - \u0627\u0644\u0635\u0648\u0645\u0627\u0644", "name:en": "Kenya - Somalia", "name:fr": "Kenya - Somalie", "right:country": "Kenya", "right:district": "Wajir", "right:province": "North Eastern", "source": "maplibrary.org"}}, {"type": "way", "id": 126924836, "nodes": [1406056407, 348404675, 348404678, 348404681, 348404683, 348404685, 348404687, 348404690, 348404692, 348404694, 348404696, 348404697, 348404698, 348404699, 348404702, 348404703, 1406056341], "tags": {"admin_level": "2", "border_type": "nation", "boundary": "administrative", "left:country": "Somalia", "name": "Ethiopia - \u0627\u0644\u0635\u0648\u0645\u0627\u0644", "name:ar": "\u0625\u062b\u064a\u0648\u0628\u064a\u0627 - \u0627\u0644\u0635\u0648\u0645\u0627\u0644", "name:en": "Ethiopia - Somalia", "name:fr": "\u00c9thiopie - Somalie", "right:country": "Ethiopia", "right:state": "Somali", "source": "maplibrary.org"}}, {"type": "way", "id": 126924842, "nodes": [1406056341, 348404704, 348404705, 348404706, 348404707, 348404709, 348404711, 348404713, 348404715, 348404717, 348404720, 348404722, 348404724, 348404727, 348404729, 348404731, 348404733, 348404735, 348404737, 348404739, 348404741, 1406056319], "tags": {"admin_level": "2", "border_type": "nation", "boundary": "administrative", "left:country": "\u0627\u0644\u0635\u0648\u0645\u0627\u0644", "name": "Ethiopia - \u0627\u0644\u0635\u0648\u0645\u0627\u0644", "name:ar": "\u0625\u062b\u064a\u0648\u0628\u064a\u0627 - \u0627\u0644\u0635\u0648\u0645\u0627\u0644", "name:en": "Ethiopia - Somalia", "name:fr": "\u00c9thiopie - Somalie", "right:country": "Ethiopia", "right:state": "Somali", "source": "maplibrary.org"}}, {"type": "way", "id": 126924845, "nodes": [1406056430, 348404623, 348404625, 348404628, 348404630, 348404632, 348404634, 348404636, 348404638, 348404641, 348404643, 348404645, 348404647, 348404650, 348404652, 348404654, 348404657, 348404660, 348404662, 348404666, 348404668, 348404670, 1406056407], "tags": {"admin_level": "2", "border_type": "nation", "boundary": "administrative", "left:country": "Somalia", "name": "Ethiopia - \u0627\u0644\u0635\u0648\u0645\u0627\u0644", "name:ar": "\u0625\u062b\u064a\u0648\u0628\u064a\u0627 - \u0627\u0644\u0635\u0648\u0645\u0627\u0644", "name:en": "Ethiopia - Somalia", "name:fr": "\u00c9thiopie - Somalie", "right:country": "Ethiopia", "right:state": "Somali", "source": "maplibrary.org"}}, {"type": "way", "id": 126924849, "nodes": [1406056319, 348404743, 348404746, 348404748, 348404750, 348404753, 11124891132, 348404755, 2510206687], "tags": {"admin_level": "2", "border_type": "nation", "boundary": "administrative", "left:country": "\u0627\u0644\u0635\u0648\u0645\u0627\u0644", "name": "Ethiopia - \u0627\u0644\u0635\u0648\u0645\u0627\u0644", "name:ar": "\u0625\u062b\u064a\u0648\u0628\u064a\u0627 - \u0627\u0644\u0635\u0648\u0645\u0627\u0644", "name:en": "Ethiopia - Somalia", "name:fr": "\u00c9thiopie - Somalie", "right:country": "Ethiopia", "right:state": "Somali", "source": "maplibrary.org"}}, {"type": "way", "id": 126924895, "nodes": [1406055785, 357060538], "tags": {"admin_level": "2", "border_type": "nation", "boundary": "administrative", "left:country": "\u0627\u0644\u0635\u0648\u0645\u0627\u0644", "name": "Kenya - \u0627\u0644\u0635\u0648\u0645\u0627\u0644", "name:ar": "\u0643\u064a\u0646\u064a\u0627 - \u0627\u0644\u0635\u0648\u0645\u0627\u0644", "name:en": "Kenya - Somalia", "name:fr": "Kenya - Somalie", "right:country": "Kenya", "right:district": "Mandera", "right:province": "North Eastern", "source": "maplibrary.org"}}, {"type": "way", "id": 126924898, "nodes": [1406050160, 348521017, 357059272], "tags": {"admin_level": "2", "border_type": "nation", "boundary": "administrative", "fixme": "position", "left:country": "\u0627\u0644\u0635\u0648\u0645\u0627\u0644", "name": "Kenya - \u0627\u0644\u0635\u0648\u0645\u0627\u0644", "name:ar": "\u0643\u064a\u0646\u064a\u0627 - \u0627\u0644\u0635\u0648\u0645\u0627\u0644", "name:en": "Kenya - Somalia", "name:fr": "Kenya - Somalie", "right:country": "Kenya", "right:district": "Wajir", "right:province": "North Eastern", "source": "maplibrary.org"}}, {"type": "way", "id": 126924899, "nodes": [11057218726, 348520945, 348404576, 11137843145], "tags": {"admin_level": "2", "border_type": "nation", "boundary": "administrative", "left:country": "\u0627\u0644\u0635\u0648\u0645\u0627\u0644", "name": "Kenya - \u0627\u0644\u0635\u0648\u0645\u0627\u0644", "name:ar": "\u0643\u064a\u0646\u064a\u0627 - \u0627\u0644\u0635\u0648\u0645\u0627\u0644", "name:en": "Kenya - Somalia", "name:fr": "Kenya - Somalie", "right:country": "Kenya", "right:district": "Mandera", "right:province": "North Eastern", "source": "maplibrary.org"}}, {"type": "way", "id": 126924902, "nodes": [1406056281, 348404564, 348404799, 348520932, 11137843136], "tags": {"admin_level": "2", "border_type": "nation", "boundary": "administrative", "left:country": "\u0627\u0644\u0635\u0648\u0645\u0627\u0644", "name": "Kenya - \u0627\u0644\u0635\u0648\u0645\u0627\u0644", "name:ar": "\u0643\u064a\u0646\u064a\u0627 - \u0627\u0644\u0635\u0648\u0645\u0627\u0644", "name:en": "Kenya - Somalia", "name:fr": "Kenya - Somalie", "right:country": "Kenya", "right:district": "Mandera", "right:province": "North Eastern", "source": "maplibrary.org"}}, {"type": "way", "id": 126924905, "nodes": [11012043040, 348404585, 348521059, 348521068, 3772944993, 3772944998, 3772945058, 3772945025, 3772945035, 3772945012, 3772945072, 3772945056, 348521080, 348404589, 2662892716], "tags": {"admin_level": "2", "border_type": "nation", "boundary": "administrative", "left:country": "Somalia", "name": "Border Kenya - Somalia", "name:ar": "\u0627\u0644\u062d\u062f\u0648\u062f \u0643\u064a\u0646\u064a\u0627 - \u0627\u0644\u0635\u0648\u0645\u0627\u0644", "right:country": "Kenya", "right:district": "Garissa", "right:province": "North Eastern", "source": "maplibrary.org"}}, {"type": "way", "id": 126924913, "nodes": [1406055658, 1406055698, 1406055730, 6395662050, 6395662052, 6395662051, 1406055922, 1406055933, 1406055937, 1406055940, 1406055942, 1406055964, 1406055969], "tags": {"admin_level": "4", "boundary": "administrative"}}, {"type": "way", "id": 126925015, "nodes": [1406056302, 1406056290]}, {"type": "way", "id": 126925025, "nodes": [1406056112, 8396389350], "tags": {"admin_level": "4", "boundary": "administrative"}}, {"type": "way", "id": 126925055, "nodes": [1406055969, 1406055978], "tags": {"admin_level": "4", "boundary": "administrative"}}, {"type": "way", "id": 126925060, "nodes": [1406056129, 1406056104], "tags": {"admin_level": "4", "boundary": "administrative"}}, {"type": "way", "id": 126925066, "nodes": [1406050240, 1406050243], "tags": {"admin_level": "4", "boundary": "administrative"}}, {"type": "way", "id": 126925069, "nodes": [1406056240, 1406056257]}, {"type": "way", "id": 126925073, "nodes": [1406056384, 1406056407]}, {"type": "way", "id": 126925088, "nodes": [1406056384, 1406056302]}, {"type": "way", "id": 126925089, "nodes": [1406050240, 1406050096], "tags": {"admin_level": "4", "boundary": "administrative"}}, {"type": "way", "id": 126925166, "nodes": [1406056107, 1406056124, 1406056129], "tags": {"admin_level": "4", "boundary": "administrative"}}, {"type": "way", "id": 126925170, "nodes": [1406056278, 1406056283, 1406056302]}, {"type": "way", "id": 126925187, "nodes": [1406056430, 1406056424, 1406056377], "tags": {"admin_level": "4", "boundary": "administrative"}}, {"type": "way", "id": 126925198, "nodes": [1406056074, 1406056102, 1406056112], "tags": {"admin_level": "4", "boundary": "administrative"}}, {"type": "way", "id": 126925204, "nodes": [1406050096, 1406050094, 1406050012], "tags": {"admin_level": "4", "boundary": "administrative"}}, {"type": "way", "id": 126925209, "nodes": [1406050169, 1406050515, 1406050521], "tags": {"admin_level": "4", "boundary": "administrative"}}, {"type": "way", "id": 126925211, "nodes": [1406050521, 1406055883, 1406055911], "tags": {"admin_level": "4", "boundary": "administrative"}}, {"type": "way", "id": 126925212, "nodes": [1406056377, 1406056369, 1406056304], "tags": {"admin_level": "4", "boundary": "administrative"}}, {"type": "way", "id": 126925223, "nodes": [1406056290, 1406056338, 1406056341], "tags": {"admin_level": "4", "boundary": "administrative"}}, {"type": "way", "id": 126925232, "nodes": [1406152694, 1406050558, 1406050562, 1406050579], "tags": {"admin_level": "4", "boundary": "administrative"}}, {"type": "way", "id": 126925238, "nodes": [1406055911, 1406055984, 1406055990], "tags": {"admin_level": "4", "boundary": "administrative"}}, {"type": "way", "id": 126925246, "nodes": [1406056257, 1406056256, 1406056319]}, {"type": "way", "id": 126925257, "nodes": [1406050012, 1406049997, 35776957, 3134140431], "tags": {"admin_level": "4", "boundary": "administrative"}}, {"type": "way", "id": 126925258, "nodes": [1406050169, 1406050160], "tags": {"admin_level": "4", "boundary": "administrative"}}, {"type": "way", "id": 126925310, "nodes": [8396389442, 1406056264, 1406056288, 1406056290], "tags": {"admin_level": "4", "boundary": "administrative"}}, {"type": "way", "id": 126925339, "nodes": [1406055978, 1406056004, 1406056062, 6569461775, 6569461195, 1406056107], "tags": {"admin_level": "4", "boundary": "administrative"}}, {"type": "way", "id": 126925355, "nodes": [1406056112, 1406056152, 1406056165, 1406056240]}, {"type": "way", "id": 126925379, "nodes": [1406056149, 1406056155, 1406056195, 1406056215], "tags": {"admin_level": "4", "boundary": "administrative"}}, {"type": "way", "id": 126925381, "nodes": [1406050243, 1406050267, 1406050441, 1406050521], "tags": {"admin_level": "4", "boundary": "administrative"}}, {"type": "way", "id": 126925452, "nodes": [1406056215, 1406056270, 1406056287, 1406056286, 1406056278], "tags": {"admin_level": "4", "boundary": "administrative"}}, {"type": "way", "id": 126925535, "nodes": [1406055990, 10197384281, 1406056073, 1406056071, 1406056060, 1406056066, 1406056074], "tags": {"admin_level": "4", "boundary": "administrative"}}, {"type": "way", "id": 126925556, "nodes": [1406056104, 1406056126, 1406056121, 1406056115, 1406056138, 1406056149], "tags": {"admin_level": "4", "boundary": "administrative"}}, {"type": "way", "id": 126925559, "nodes": [1406056304, 1406056303, 1406056271, 1406056242, 1406056188, 1406056129], "tags": {"admin_level": "4", "boundary": "administrative"}}, {"type": "way", "id": 126925597, "nodes": [1406056278, 1406056275, 1406056266, 1406056244, 1406056214, 1406056190, 8396389458], "tags": {"admin_level": "4", "boundary": "administrative"}}, {"type": "way", "id": 157708992, "nodes": [3134139026, 2662892716], "tags": {"admin_level": "2", "border_type": "territorial", "boundary": "administrative", "maritime": "yes", "source": "Outer Limit of the Exclusive Economic Zone of the Federal Republic of Somalia, 30 June 2014"}}, {"type": "way", "id": 188767029, "nodes": [3134140553, 3134140552, 3134140551, 3134140550, 3134140549, 3134140548], "tags": {"admin_level": "2", "border_type": "territorial", "boundary": "administrative", "maritime": "yes", "source": "12 nm measured from coastline"}}, {"type": "way", "id": 188777394, "nodes": [3134140429, 1994053672, 1699640044, 3134139028, 3134139027, 3134138958, 3134138959, 3134138960, 3134138961, 3134138962, 1699639864, 3134138963, 3134138964, 1699639867, 3134138965, 3134138966, 3134138967, 3134138968, 3134138969, 3134138970, 3134138971, 3134138972, 3134138973, 3134138974, 3134138975, 1699639870, 3134138976, 3134138977, 3134138978, 3134138979, 3134138980, 3134138981, 3134138982, 3134138983, 1699639871, 3134138984, 3134138985, 3134138986, 3134138987, 3134138988, 3134138989, 3134138990, 3134138991, 3134138992, 3134138993, 3134138994, 3134138995, 1699639872, 3134138996, 3134138997, 3134138998, 3134138999, 3134139000, 3134139001, 3134139002, 3134139003, 3134139004, 1699639873, 3134139005, 3134139006, 3134139007, 3134139008, 3134139009, 3134139010, 3134139011, 1699639875, 3134139012, 3134139013, 3134139014, 3134139015, 3134139016, 3134139017, 3134139018, 3134139019, 3134139020, 3134139021, 3134139022, 1699639892, 3134139023, 3134139024, 3134139025, 1699639895, 1699639898, 3134139026], "tags": {"admin_level": "2", "border_type": "territorial", "boundary": "administrative", "maritime": "yes", "source": "12 nm measured from coastline"}}, {"type": "way", "id": 188777397, "nodes": [3134140431, 1699640045, 3134140430, 3134140429], "tags": {"admin_level": "2", "border_type": "territorial", "boundary": "administrative", "maritime": "yes", "source": "12 nm measured from coastline"}}, {"type": "way", "id": 188777400, "nodes": [3134138928, 1994053675, 3134138927, 3134138926, 3134138925, 3134138924, 3134138923, 3134138922, 3134138921, 3134138920, 3134138919, 3134138918, 3134138917, 3134138916, 3134138915, 3134138914, 3134140457, 3134140456, 3134140455, 3134140454, 3134140453, 1699640046, 3134140452, 3134140451, 3134140450, 3134140449, 3134140448, 3134140447, 3134140446, 3134140445, 3134140444, 3134140443, 3134140442, 3134140441, 3134140440, 3134140439, 3134140438, 3134140437, 3134140436, 3134140435, 3134140434, 3134140433, 3134140432, 3134140431], "tags": {"admin_level": "2", "border_type": "territorial", "boundary": "administrative", "maritime": "yes", "source": "12 nm measured from coastline"}}, {"type": "way", "id": 188777403, "nodes": [3134140548, 1994053679, 3134140547, 1699640058, 3134140546, 3134140545, 3134140544, 3134140543, 3134140542, 3134140541, 3134140540, 3134140539, 3134140538, 3134140537, 3134140536, 3134140535, 3134140534, 3134140533, 1699640055, 3134140532, 3134140531, 3134140530, 3134140529, 3134138928], "tags": {"admin_level": "2", "border_type": "territorial", "boundary": "administrative", "maritime": "yes", "source": "12 nm measured from coastline"}}, {"type": "way", "id": 243641303, "nodes": [2510206687, 348404757, 348404759, 348404762, 348404764, 348404765, 348404766, 348404767, 348404768, 348404769, 348404770, 348404774, 348404776, 348404777, 348404779, 348404781, 5518905650, 5518905651, 5518905652, 5518905653, 5518905654, 5518905657, 5518905656, 5518905655, 5518905662, 5518905661, 5518905660, 5518905659, 5518905658, 5518905664, 5518905663, 348404783, 5518905665, 5518905666, 5518905669, 5518905668, 5518905667, 5518905670, 5518905671, 348404785, 348404788], "tags": {"admin_level": "2", "border_type": "nation", "boundary": "administrative", "left:country": "\u0627\u0644\u0635\u0648\u0645\u0627\u0644", "name": "Ethiopia - \u0627\u0644\u0635\u0648\u0645\u0627\u0644", "name:ar": "\u0625\u062b\u064a\u0648\u0628\u064a\u0627 - \u0627\u0644\u0635\u0648\u0645\u0627\u0644", "name:en": "Ethiopia - Somalia", "name:fr": "\u00c9thiopie - Somalie", "right:country": "Ethiopia", "right:state": "Somali", "source": "maplibrary.org"}}, {"type": "way", "id": 261605196, "nodes": [2544755345, 2672071019, 2672071018, 2672071016, 2672071014, 2672071012, 2672071010, 2672071006, 2275588565, 4532167215, 4532166688, 348521030, 11012043039], "tags": {"admin_level": "2", "border_type": "nation", "boundary": "administrative", "left:country": "\u0627\u0644\u0635\u0648\u0645\u0627\u0644", "name": "Kenya - \u0627\u0644\u0635\u0648\u0645\u0627\u0644", "name:ar": "\u0643\u064a\u0646\u064a\u0627 - \u0627\u0644\u0635\u0648\u0645\u0627\u0644", "name:en": "Kenya - Somalia", "name:fr": "Kenya - Somalie", "right:country": "Kenya", "right:district": "Garissa", "right:province": "North Eastern", "source": "maplibrary.org"}}, {"type": "way", "id": 311030199, "nodes": [3165622245, 348404795, 1406056281], "tags": {"admin_level": "2", "border_type": "nation", "description": "drains and tunnels in Kenya", "layer": "1", "left:country": "\u0627\u0644\u0635\u0648\u0645\u0627\u0644", "name": "Kenya - \u0627\u0644\u0635\u0648\u0645\u0627\u0644", "name:ar": "\u0643\u064a\u0646\u064a\u0627 - \u0627\u0644\u0635\u0648\u0645\u0627\u0644", "name:en": "Kenya - Somalia", "name:fr": "Kenya - Somalie", "right:country": "Kenya", "right:district": "Mandera", "right:province": "North Eastern", "source": "maplibrary.org;aerial imagery", "tunnel": "flooded", "waterway": "drain"}}, {"type": "way", "id": 497701073, "nodes": [1406050579, 1406050583, 9516000039, 9516000040, 9516000041, 9516000042, 9516000071, 9516000072, 9516000075, 9516000076, 1406054401, 3136498639, 10858937987, 8494615416, 9490093935, 1406055085, 1406055165, 1406055307, 1406055343, 1406055362, 1406055375, 1406055443, 1406055444, 1406055533, 1406055543, 1406055556, 1406055567, 1406055575, 1406055577, 1406055580, 1406055597, 1406055605, 1406055609, 1406055612, 1406055615, 1406055647, 7912107911, 1406055652, 1406055649, 1406055636, 1406055628, 8926872109, 1406514988, 1406055282, 8710929947, 1406055244, 1406055238, 314263245, 1406055301, 1406055297, 1406055305, 1406055349, 1406055347, 9524383211, 9524401428, 9524383210, 9524383209, 11435472300, 9524383206, 9513675556, 9513675568, 1406055473, 1406055471, 1406055476, 8726364794, 8726364793, 8726158678, 9431510782, 1406055584, 8728742356, 1406055601, 1406055658], "tags": {"admin_level": "4", "boundary": "administrative"}}, {"type": "way", "id": 904068728, "nodes": [8396389350, 1406056230], "tags": {"admin_level": "4", "boundary": "administrative"}}, {"type": "way", "id": 904068735, "nodes": [1406056230, 8396389442], "tags": {"admin_level": "4", "boundary": "administrative"}}, {"type": "way", "id": 904068737, "nodes": [8396389458, 1406056230], "tags": {"admin_level": "4", "boundary": "administrative"}}, {"type": "way", "id": 1185480134, "nodes": [11012043039, 1406047774], "tags": {"admin_level": "2", "border_type": "nation", "boundary": "administrative", "left:country": "\u0627\u0644\u0635\u0648\u0645\u0627\u0644", "name": "Kenya - \u0627\u0644\u0635\u0648\u0645\u0627\u0644", "name:ar": "\u0643\u064a\u0646\u064a\u0627 - \u0627\u0644\u0635\u0648\u0645\u0627\u0644", "name:en": "Kenya - Somalia", "name:fr": "Kenya - Somalie", "right:country": "Kenya", "right:district": "Garissa", "right:province": "North Eastern", "source": "maplibrary.org"}}, {"type": "way", "id": 1185480135, "nodes": [1406047774, 11012043040], "tags": {"admin_level": "2", "border_type": "nation", "boundary": "administrative", "left:country": "Somalia", "name": "Border Kenya - Somalia", "name:ar": "\u0627\u0644\u062d\u062f\u0648\u062f \u0643\u064a\u0646\u064a\u0627 - \u0627\u0644\u0635\u0648\u0645\u0627\u0644", "right:country": "Kenya", "right:district": "Garissa", "right:province": "North Eastern", "source": "maplibrary.org"}}, {"type": "way", "id": 1190881925, "nodes": [11057218725, 1406055785], "tags": {"admin_level": "2", "border_type": "nation", "boundary": "administrative", "left:country": "\u0627\u0644\u0635\u0648\u0645\u0627\u0644", "name": "Kenya - \u0627\u0644\u0635\u0648\u0645\u0627\u0644", "name:ar": "\u0643\u064a\u0646\u064a\u0627 - \u0627\u0644\u0635\u0648\u0645\u0627\u0644", "name:en": "Kenya - Somalia", "name:fr": "Kenya - Somalie", "right:country": "Kenya", "right:district": "Mandera", "right:province": "North Eastern", "source": "maplibrary.org"}}, {"type": "way", "id": 1190881926, "nodes": [1406056079, 11057218726], "tags": {"admin_level": "2", "border_type": "nation", "boundary": "administrative", "left:country": "\u0627\u0644\u0635\u0648\u0645\u0627\u0644", "name": "Kenya - \u0627\u0644\u0635\u0648\u0645\u0627\u0644", "name:ar": "\u0643\u064a\u0646\u064a\u0627 - \u0627\u0644\u0635\u0648\u0645\u0627\u0644", "name:en": "Kenya - Somalia", "name:fr": "Kenya - Somalie", "right:country": "Kenya", "right:district": "Mandera", "right:province": "North Eastern", "source": "maplibrary.org"}}, {"type": "way", "id": 1190881928, "nodes": [11137843137, 5248113440, 348404568, 348404572, 1406056079], "tags": {"admin_level": "2", "border_type": "nation", "boundary": "administrative", "left:country": "\u0627\u0644\u0635\u0648\u0645\u0627\u0644", "name": "Kenya - \u0627\u0644\u0635\u0648\u0645\u0627\u0644", "name:ar": "\u0643\u064a\u0646\u064a\u0627 - \u0627\u0644\u0635\u0648\u0645\u0627\u0644", "name:en": "Kenya - Somalia", "name:fr": "Kenya - Somalie", "right:country": "Kenya", "right:district": "Mandera", "right:province": "North Eastern", "source": "maplibrary.org"}}, {"type": "way", "id": 1194249741, "nodes": [11085449876, 1406050160], "tags": {"admin_level": "2", "border_type": "nation", "boundary": "administrative", "left:country": "\u0627\u0644\u0635\u0648\u0645\u0627\u0644", "name": "Kenya - \u0627\u0644\u0635\u0648\u0645\u0627\u0644", "name:ar": "\u0643\u064a\u0646\u064a\u0627 - \u0627\u0644\u0635\u0648\u0645\u0627\u0644", "name:en": "Kenya - Somalia", "name:fr": "Kenya - Somalie", "right:country": "Kenya", "right:district": "Wajir", "right:province": "North Eastern", "source": "maplibrary.org"}}, {"type": "way", "id": 1197951071, "nodes": [3134140553, 1406152694], "tags": {"admin_level": "4", "boundary": "administrative", "maritime": "yes"}}, {"type": "way", "id": 1201267291, "nodes": [11137843132, 3165622245], "tags": {"admin_level": "2", "border_type": "nation", "boundary": "administrative", "left:country": "\u0627\u0644\u0635\u0648\u0645\u0627\u0644", "name": "Kenya - \u0627\u0644\u0635\u0648\u0645\u0627\u0644", "name:ar": "\u0643\u064a\u0646\u064a\u0627 - \u0627\u0644\u0635\u0648\u0645\u0627\u0644", "name:en": "Kenya - Somalia", "name:fr": "Kenya - Somalie", "right:country": "Kenya", "right:district": "Mandera", "right:province": "North Eastern", "source": "maplibrary.org"}}, {"type": "way", "id": 1201267300, "nodes": [11137843136, 348520903, 11057218728], "tags": {"admin_level": "2", "border_type": "nation", "boundary": "administrative", "left:country": "\u0627\u0644\u0635\u0648\u0645\u0627\u0644", "name": "Kenya - \u0627\u0644\u0635\u0648\u0645\u0627\u0644", "name:ar": "\u0643\u064a\u0646\u064a\u0627 - \u0627\u0644\u0635\u0648\u0645\u0627\u0644", "name:en": "Kenya - Somalia", "name:fr": "Kenya - Somalie", "right:country": "Kenya", "right:district": "Mandera", "right:province": "North Eastern", "source": "maplibrary.org"}}, {"type": "way", "id": 1201267302, "nodes": [11057218728, 348520916, 11137843137], "tags": {"admin_level": "2", "border_type": "nation", "boundary": "administrative", "left:country": "\u0627\u0644\u0635\u0648\u0645\u0627\u0644", "name": "Kenya - \u0627\u0644\u0635\u0648\u0645\u0627\u0644", "name:ar": "\u0643\u064a\u0646\u064a\u0627 - \u0627\u0644\u0635\u0648\u0645\u0627\u0644", "name:en": "Kenya - Somalia", "name:fr": "Kenya - Somalie", "right:country": "Kenya", "right:district": "Mandera", "right:province": "North Eastern", "source": "maplibrary.org"}}, {"type": "way", "id": 1201267309, "nodes": [11137843145, 11057218725], "tags": {"admin_level": "2", "border_type": "nation", "boundary": "administrative", "left:country": "\u0627\u0644\u0635\u0648\u0645\u0627\u0644", "name": "Kenya - \u0627\u0644\u0635\u0648\u0645\u0627\u0644", "name:ar": "\u0643\u064a\u0646\u064a\u0627 - \u0627\u0644\u0635\u0648\u0645\u0627\u0644", "name:en": "Kenya - Somalia", "name:fr": "Kenya - Somalie", "right:country": "Kenya", "right:district": "Mandera", "right:province": "North Eastern", "source": "maplibrary.org"}}, {"type": "relation", "id": 1720052, "members": [{"type": "node", "ref": 36155607, "role": "admin_centre"}, {"type": "node", "ref": 43527998, "role": "label"}, {"type": "way", "ref": 126925212, "role": "outer"}, {"type": "way", "ref": 126925187, "role": "outer"}, {"type": "way", "ref": 126924845, "role": "outer"}, {"type": "way", "ref": 126924836, "role": "outer"}, {"type": "way", "ref": 126925223, "role": "outer"}, {"type": "way", "ref": 126925310, "role": "outer"}, {"type": "way", "ref": 904068735, "role": "outer"}, {"type": "way", "ref": 904068737, "role": "outer"}, {"type": "way", "ref": 126925597, "role": "outer"}, {"type": "way", "ref": 126925452, "role": "outer"}, {"type": "way", "ref": 126925379, "role": "outer"}, {"type": "way", "ref": 126925556, "role": "outer"}, {"type": "way", "ref": 126925060, "role": "outer"}, {"type": "way", "ref": 126925559, "role": "outer"}], "tags": {"ISO3166-2": "SO-BK", "admin_level": "5", "boundary": "administrative", "name": "Bakool \u0628\u0627\u0643\u0648\u0644", "name:ar": "\u0628\u0627\u0643\u0648\u0644", "name:de": "Bakool", "name:en": "Bakool", "name:es": "Bakool", "name:fr": "Bakool", "name:ru": "\u0411\u0430\u043a\u043e\u043b\u044c", "name:zh": "\u5df4\u79d1\u52d2\u5dde", "source": "UN OCHA COD", "type": "boundary", "wikidata": "Q282471", "wikipedia": "ar:\u0628\u0643\u0648\u0644"}}, {"type": "relation", "id": 1720057, "members": [{"type": "node", "ref": 1404233530, "role": "admin_centre"}, {"type": "node", "ref": 43528040, "role": "label"}, {"type": "way", "ref": 1190881925, "role": "outer"}, {"type": "way", "ref": 1201267309, "role": "outer"}, {"type": "way", "ref": 126924899, "role": "outer"}, {"type": "way", "ref": 1190881926, "role": "outer"}, {"type": "way", "ref": 1190881928, "role": "outer"}, {"type": "way", "ref": 1201267302, "role": "outer"}, {"type": "way", "ref": 1201267300, "role": "outer"}, {"type": "way", "ref": 126924902, "role": "outer"}, {"type": "way", "ref": 311030199, "role": "outer"}, {"type": "way", "ref": 1201267291, "role": "outer"}, {"type": "way", "ref": 31316551, "role": "outer"}, {"type": "way", "ref": 243641303, "role": "outer"}, {"type": "way", "ref": 126924849, "role": "outer"}, {"type": "way", "ref": 126924842, "role": "outer"}, {"type": "way", "ref": 126925223, "role": "outer"}, {"type": "way", "ref": 126925310, "role": "outer"}, {"type": "way", "ref": 904068735, "role": "outer"}, {"type": "way", "ref": 904068728, "role": "outer"}, {"type": "way", "ref": 126925025, "role": "outer"}, {"type": "way", "ref": 126925198, "role": "outer"}, {"type": "way", "ref": 126925535, "role": "outer"}, {"type": "way", "ref": 126925238, "role": "outer"}, {"type": "way", "ref": 126925211, "role": "outer"}, {"type": "way", "ref": 126925209, "role": "outer"}, {"type": "way", "ref": 126925258, "role": "outer"}, {"type": "way", "ref": 1194249741, "role": "outer"}, {"type": "way", "ref": 31886935, "role": "outer"}, {"type": "way", "ref": 126924895, "role": "outer"}, {"type": "node", "ref": 1395957416, "role": "admin_centre"}], "tags": {"ISO3166-2": "SO-GE", "admin_level": "5", "boundary": "administrative", "name": "Gedo \u062c\u062f\u0648", "name:ar": "\u062c\u062f\u0648", "name:de": "Gedo", "name:en": "Gedo", "name:es": "Gedo", "name:fr": "Gedo", "name:it": "Ghedo", "name:ru": "\u0413\u0435\u0434\u043e", "name:zh": "\u76d6\u591a\u5dde", "type": "boundary", "wikidata": "Q856719", "wikipedia": "ar:\u062c\u062f\u0648"}}, {"type": "relation", "id": 1720123, "members": [{"type": "way", "ref": 126924842, "role": "outer"}, {"type": "way", "ref": 126925223, "role": "outer"}, {"type": "way", "ref": 126925310, "role": "outer"}, {"type": "way", "ref": 904068735, "role": "outer"}, {"type": "way", "ref": 904068728, "role": "outer"}, {"type": "way", "ref": 126925025, "role": "outer"}, {"type": "way", "ref": 126925355, "role": "outer"}, {"type": "way", "ref": 126925069, "role": "outer"}, {"type": "way", "ref": 126925246, "role": "outer"}, {"type": "node", "ref": 1404225468, "role": "admin_centre"}], "tags": {"admin_level": "6", "boundary": "administrative", "name": "Luuq \u0644\u0648\u0642", "name:ar": "\u0644\u0648\u0642", "name:en": "Luuq District", "name:fr": "Luuq", "source": "UN OCHA COD", "type": "boundary", "wikidata": "Q6706074"}}, {"type": "relation", "id": 1720131, "members": [{"type": "way", "ref": 126924836, "role": "outer"}, {"type": "way", "ref": 126925073, "role": "outer"}, {"type": "way", "ref": 126925088, "role": "outer"}, {"type": "way", "ref": 126925015, "role": "outer"}, {"type": "way", "ref": 126925223, "role": "outer"}, {"type": "node", "ref": 1404223298, "role": "admin_centre"}], "tags": {"admin_level": "6", "boundary": "administrative", "name": "Rab Dhuure", "name:en": "Rabdhure District", "name:fr": "Rabdhure", "source": "UN OCHA COD", "type": "boundary", "wikidata": "Q17069671"}}, {"type": "relation", "id": 1720137, "members": [{"type": "way", "ref": 126925015, "role": "outer"}, {"type": "way", "ref": 126925170, "role": "outer"}, {"type": "way", "ref": 126925597, "role": "outer"}, {"type": "way", "ref": 904068737, "role": "outer"}, {"type": "way", "ref": 904068735, "role": "outer"}, {"type": "way", "ref": 126925310, "role": "outer"}, {"type": "node", "ref": 1404227318, "role": "admin_centre"}], "tags": {"admin_level": "6", "boundary": "administrative", "name": "Waajid \u0648\u0627\u0627\u062c\u064a\u062f", "name:ar": "\u0648\u0627\u0627\u062c\u064a\u062f", "name:en": "Wajid District", "name:fr": "Wajid", "source": "UN OCHA COD", "type": "boundary", "wikidata": "Q7960700"}}, {"type": "relation", "id": 13702731, "members": [{"type": "way", "ref": 126925055, "role": "outer"}, {"type": "way", "ref": 126924913, "role": "outer"}, {"type": "way", "ref": 497701073, "role": "outer"}, {"type": "way", "ref": 126925232, "role": "outer"}, {"type": "way", "ref": 1197951071, "role": "outer"}, {"type": "way", "ref": 188767029, "role": "outer"}, {"type": "way", "ref": 188777403, "role": "outer"}, {"type": "way", "ref": 188777400, "role": "outer"}, {"type": "way", "ref": 126925257, "role": "outer"}, {"type": "way", "ref": 126925204, "role": "outer"}, {"type": "way", "ref": 126925089, "role": "outer"}, {"type": "way", "ref": 126925066, "role": "outer"}, {"type": "way", "ref": 126925381, "role": "outer"}, {"type": "way", "ref": 126925211, "role": "outer"}, {"type": "way", "ref": 126925238, "role": "outer"}, {"type": "way", "ref": 126925535, "role": "outer"}, {"type": "way", "ref": 126925198, "role": "outer"}, {"type": "way", "ref": 126925025, "role": "outer"}, {"type": "way", "ref": 904068728, "role": "outer"}, {"type": "way", "ref": 904068735, "role": "outer"}, {"type": "way", "ref": 126925310, "role": "outer"}, {"type": "way", "ref": 126925223, "role": "outer"}, {"type": "way", "ref": 126924836, "role": "outer"}, {"type": "way", "ref": 126924845, "role": "outer"}, {"type": "way", "ref": 126925187, "role": "outer"}, {"type": "way", "ref": 126925212, "role": "outer"}, {"type": "way", "ref": 126925559, "role": "outer"}, {"type": "way", "ref": 126925166, "role": "outer"}, {"type": "way", "ref": 126925339, "role": "outer"}, {"type": "node", "ref": 43527946, "role": "admin_centre"}, {"type": "relation", "ref": 1720052, "role": "subarea"}, {"type": "relation", "ref": 1720055, "role": "subarea"}, {"type": "relation", "ref": 1720060, "role": "subarea"}], "tags": {"admin_level": "4", "boundary": "administrative", "name": "Koonfur Galbeed \u062c\u0646\u0648\u0628 \u063a\u0631\u0628", "name:ar": "\u062c\u0646\u0648\u0628 \u063a\u0631\u0628", "name:en": "South West", "name:so": "Koonfur Galbeed", "name:zh": "\u7d22\u9a6c\u91cc\u897f\u5357\u56fd", "type": "boundary", "wikidata": "Q1136259"}}, {"type": "relation", "id": 13702732, "members": [{"type": "way", "ref": 311030199, "role": "outer"}, {"type": "way", "ref": 126924902, "role": "outer"}, {"type": "way", "ref": 1201267300, "role": "outer"}, {"type": "way", "ref": 1201267302, "role": "outer"}, {"type": "way", "ref": 1190881928, "role": "outer"}, {"type": "way", "ref": 1190881926, "role": "outer"}, {"type": "way", "ref": 126924899, "role": "outer"}, {"type": "way", "ref": 1201267309, "role": "outer"}, {"type": "way", "ref": 1190881925, "role": "outer"}, {"type": "way", "ref": 126924895, "role": "outer"}, {"type": "way", "ref": 31886935, "role": "outer"}, {"type": "way", "ref": 1194249741, "role": "outer"}, {"type": "way", "ref": 126924898, "role": "outer"}, {"type": "way", "ref": 31886922, "role": "outer"}, {"type": "way", "ref": 261605196, "role": "outer"}, {"type": "way", "ref": 1185480134, "role": "outer"}, {"type": "way", "ref": 1185480135, "role": "outer"}, {"type": "way", "ref": 126924905, "role": "outer"}, {"type": "way", "ref": 157708992, "role": "outer"}, {"type": "way", "ref": 188777394, "role": "outer"}, {"type": "way", "ref": 188777397, "role": "outer"}, {"type": "way", "ref": 126925257, "role": "outer"}, {"type": "way", "ref": 126925204, "role": "outer"}, {"type": "way", "ref": 126925089, "role": "outer"}, {"type": "way", "ref": 126925066, "role": "outer"}, {"type": "way", "ref": 126925381, "role": "outer"}, {"type": "way", "ref": 126925211, "role": "outer"}, {"type": "way", "ref": 126925238, "role": "outer"}, {"type": "way", "ref": 126925535, "role": "outer"}, {"type": "way", "ref": 126925198, "role": "outer"}, {"type": "way", "ref": 126925025, "role": "outer"}, {"type": "way", "ref": 904068728, "role": "outer"}, {"type": "way", "ref": 904068735, "role": "outer"}, {"type": "way", "ref": 126925310, "role": "outer"}, {"type": "way", "ref": 126925223, "role": "outer"}, {"type": "way", "ref": 126924842, "role": "outer"}, {"type": "way", "ref": 126924849, "role": "outer"}, {"type": "way", "ref": 243641303, "role": "outer"}, {"type": "way", "ref": 31316551, "role": "outer"}, {"type": "way", "ref": 1201267291, "role": "outer"}, {"type": "relation", "ref": 1720057, "role": "subarea"}, {"type": "relation", "ref": 1720061, "role": "subarea"}, {"type": "relation", "ref": 1720059, "role": "subarea"}, {"type": "node", "ref": 43528307, "role": "admin_centre"}], "tags": {"admin_level": "4", "boundary": "administrative", "name": "Jubaland \u062c\u0648\u0628\u0627\u0644\u0627\u0646\u062f", "name:ar": "\u062c\u0648\u0628\u0627\u0644\u0627\u0646\u062f", "name:en": "Jubaland", "name:so": "Jubaland", "name:zh": "\u6731\u5df4\u5170", "type": "boundary", "wikidata": "Q949280"}}]}